Shift_Reg/shift.v
module MUX(i3,i2,i1,i0,s1,s0,out);

input i3,i2,i1,i0,s1,s0;

output out;

wire n_s1,n_s0,t3,t2,t1,t0;
	
not n1(n_s1,s1);
not n0(n_s0,s0);
and a0(t0,i0,n_s1,n_s0);
and a1(t1,i1,n_s1,s0);
and a2(t2,i2,s1,n_s0);
and a3(t3,i3,s1,s0);
or o0(out,t0,t1,t2,t3);
	
endmodule

module shift(IP3,IP2,IP1,IP0,SEL1,SEL0,OP3,OP2,OP1,OP0);

input IP3;
input IP2;
input IP1;
input IP0;
input SEL1;
input SEL0;

output OP3;
output OP2;
output OP1;
output OP0;

wire OP3,OP2,OP1,OP0;
	
	
MUX m0( .i3(IP1), .i2(IP1),  .i1(1'b1), .i0(IP0), .s1(SEL1), .s0(SEL0), .out(OP0) );
MUX m1( .i3(IP2), .i2(IP2),  .i1(IP0),  .i0(IP1), .s1(SEL1), .s0(SEL0), .out(OP1) );
MUX m2( .i3(IP3), .i2(IP3),  .i1(IP1),  .i0(IP2), .s1(SEL1), .s0(SEL0), .out(OP2) );
MUX m3( .i3(IP0), .i2(1'b1), .i1(IP2),  .i0(IP3), .s1(SEL1), .s0(SEL0), .out(OP3) );
	
endmodule

module testbench();


reg IP3,IP2,IP1,IP0,SEL1,SEL0;
wire OP3,OP2,OP1,OP0;

shift f1(IP3,IP2,IP1,IP0,SEL1,SEL0,OP3,OP2,OP1,OP0);

initial 
begin
	
$monitor("IP = %b%b%b%b :  SEL = %b%b  :  OUT = %b%b%b",IP3,IP2,IP1,IP0,SEL1,SEL0,OP3,OP2,OP1,OP0);
$dumpfile("shift.vcd");
$dumpvars;
	

    	IP3=1'b0;
		IP2=1'b0;
		IP1=1'b0;
		IP0=1'b0;	
		SEL1=1'b0;
		SEL0=1'b0;
		#10
		IP3=1'b0;
		IP2=1'b0;
		IP1=1'b0;
		IP0=1'b1;		
		SEL1=1'b0;
		SEL0=1'b0;
		#10
		IP3=1'b0;
		IP2=1'b0;
		IP1=1'b1;
		IP0=1'b0;		
		SEL1=1'b0;
		SEL0=1'b0;
		#10
		IP3=1'b0;
		IP2=1'b0;
		IP1=1'b1;
		IP0=1'b1;		
		SEL1=1'b0;
		SEL0=1'b0;
		#10
		IP3=1'b0;
		IP2=1'b1;
		IP1=1'b0;
		IP0=1'b0;	
		SEL1=1'b0;
		SEL0=1'b0;
		#10
		IP3=1'b0;
		IP2=1'b1;
		IP1=1'b0;
		IP0=1'b1;		
		SEL1=1'b0;
		SEL0=1'b0;
		#10
		IP3=1'b0;
		IP2=1'b1;
		IP1=1'b1;
		IP0=1'b0;		
		SEL1=1'b0;
		SEL0=1'b0;
		#10
		IP3=1'b0;
		IP2=1'b1;
		IP1=1'b1;
		IP0=1'b1;		
		SEL1=1'b0;
		SEL0=1'b0;
		#10
		IP3=1'b1;
		IP2=1'b0;
		IP1=1'b0;
		IP0=1'b0;	
		SEL1=1'b0;
		SEL0=1'b0;
		#10
		IP3=1'b1;
		IP2=1'b0;
		IP1=1'b0;
		IP0=1'b1;		
		SEL1=1'b0;
		SEL0=1'b0;
		#10
		IP3=1'b1;
		IP2=1'b0;
		IP1=1'b1;
		IP0=1'b0;		
		SEL1=1'b0;
		SEL0=1'b0;
		#10
		IP3=1'b1;
		IP2=1'b0;
		IP1=1'b1;
		IP0=1'b1;		
		SEL1=1'b0;
		SEL0=1'b0;
		#10
		IP3=1'b1;
		IP2=1'b1;
		IP1=1'b0;
		IP0=1'b0;	
		SEL1=1'b0;
		SEL0=1'b0;
		#10
		IP3=1'b1;
		IP2=1'b1;
		IP1=1'b0;
		IP0=1'b1;		
		SEL1=1'b0;
		SEL0=1'b0;
		#10
		IP3=1'b1;
		IP2=1'b1;
		IP1=1'b1;
		IP0=1'b0;		
		SEL1=1'b0;
		SEL0=1'b0;
		#10
		IP3=1'b1;
		IP2=1'b1;
		IP1=1'b1;
		IP0=1'b1;		
		SEL1=1'b0;
		SEL0=1'b0;
		#10;
		
		IP3=1'b0;
		IP2=1'b0;
		IP1=1'b0;
		IP0=1'b0;	
		SEL1=1'b0;
		SEL0=1'b1;
		#10
		IP3=1'b0;
		IP2=1'b0;
		IP1=1'b0;
		IP0=1'b1;		
		SEL1=1'b0;
		SEL0=1'b1;
		#10
		IP3=1'b0;
		IP2=1'b0;
		IP1=1'b1;
		IP0=1'b0;		
		SEL1=1'b0;
		SEL0=1'b1;
		#10
		IP3=1'b0;
		IP2=1'b0;
		IP1=1'b1;
		IP0=1'b1;		
		SEL1=1'b0;
		SEL0=1'b1;
		#10
		IP3=1'b0;
		IP2=1'b1;
		IP1=1'b0;
		IP0=1'b0;	
		SEL1=1'b0;
		SEL0=1'b1;
		#10
		IP3=1'b0;
		IP2=1'b1;
		IP1=1'b0;
		IP0=1'b1;		
		SEL1=1'b0;
		SEL0=1'b1;
		#10
		IP3=1'b0;
		IP2=1'b1;
		IP1=1'b1;
		IP0=1'b0;		
		SEL1=1'b0;
		SEL0=1'b1;
		#10
		IP3=1'b0;
		IP2=1'b1;
		IP1=1'b1;
		IP0=1'b1;		
		SEL1=1'b0;
		SEL0=1'b1;
		#10
		IP3=1'b1;
		IP2=1'b0;
		IP1=1'b0;
		IP0=1'b0;	
		SEL1=1'b0;
		SEL0=1'b1;
		#10
		IP3=1'b1;
		IP2=1'b0;
		IP1=1'b0;
		IP0=1'b1;		
		SEL1=1'b0;
		SEL0=1'b1;
		#10
		IP3=1'b1;
		IP2=1'b0;
		IP1=1'b1;
		IP0=1'b0;		
		SEL1=1'b0;
		SEL0=1'b1;
		#10
		IP3=1'b1;
		IP2=1'b0;
		IP1=1'b1;
		IP0=1'b1;		
		SEL1=1'b0;
		SEL0=1'b1;
		#10
		IP3=1'b1;
		IP2=1'b1;
		IP1=1'b0;
		IP0=1'b0;	
		SEL1=1'b0;
		SEL0=1'b1;
		#10
		IP3=1'b1;
		IP2=1'b1;
		IP1=1'b0;
		IP0=1'b1;		
		SEL1=1'b0;
		SEL0=1'b1;
		#10
		IP3=1'b1;
		IP2=1'b1;
		IP1=1'b1;
		IP0=1'b0;		
		SEL1=1'b0;
		SEL0=1'b1;
		#10
		IP3=1'b1;
		IP2=1'b1;
		IP1=1'b1;
		IP0=1'b1;		
		SEL1=1'b0;
		SEL0=1'b1;
		#10
		
		IP3=1'b0;
		IP2=1'b0;
		IP1=1'b0;
		IP0=1'b0;	
		SEL1=1'b1;
		SEL0=1'b0;
		#10
		IP3=1'b0;
		IP2=1'b0;
		IP1=1'b0;
		IP0=1'b1;		
		SEL1=1'b1;
		SEL0=1'b0;
		#10
		IP3=1'b0;
		IP2=1'b0;
		IP1=1'b1;
		IP0=1'b0;		
		SEL1=1'b1;
		SEL0=1'b0;
		#10
		IP3=1'b0;
		IP2=1'b0;
		IP1=1'b1;
		IP0=1'b1;		
		SEL1=1'b1;
		SEL0=1'b0;
		#10
		IP3=1'b0;
		IP2=1'b1;
		IP1=1'b0;
		IP0=1'b0;	
		SEL1=1'b1;
		SEL0=1'b0;
		#10
		IP3=1'b0;
		IP2=1'b1;
		IP1=1'b0;
		IP0=1'b1;		
		SEL1=1'b1;
		SEL0=1'b0;
		#10
		IP3=1'b0;
		IP2=1'b1;
		IP1=1'b1;
		IP0=1'b0;		
		SEL1=1'b1;
		SEL0=1'b0;
		#10
		IP3=1'b0;
		IP2=1'b1;
		IP1=1'b1;
		IP0=1'b1;		
		SEL1=1'b1;
		SEL0=1'b0;
		#10
		IP3=1'b1;
		IP2=1'b0;
		IP1=1'b0;
		IP0=1'b0;	
		SEL1=1'b1;
		SEL0=1'b0;
		#10
		IP3=1'b1;
		IP2=1'b0;
		IP1=1'b0;
		IP0=1'b1;		
		SEL1=1'b1;
		SEL0=1'b0;
		#10
		IP3=1'b1;
		IP2=1'b0;
		IP1=1'b1;
		IP0=1'b0;		
		SEL1=1'b1;
		SEL0=1'b0;
		#10
		IP3=1'b1;
		IP2=1'b0;
		IP1=1'b1;
		IP0=1'b1;		
		SEL1=1'b1;
		SEL0=1'b0;
		#10
		IP3=1'b1;
		IP2=1'b1;
		IP1=1'b0;
		IP0=1'b0;	
		SEL1=1'b1;
		SEL0=1'b0;
		#10
		IP3=1'b1;
		IP2=1'b1;
		IP1=1'b0;
		IP0=1'b1;		
		SEL1=1'b1;
		SEL0=1'b0;
		#10
		IP3=1'b1;
		IP2=1'b1;
		IP1=1'b1;
		IP0=1'b0;		
		SEL1=1'b1;
		SEL0=1'b0;
		#10
		IP3=1'b1;
		IP2=1'b1;
		IP1=1'b1;
		IP0=1'b1;		
		SEL1=1'b1;
		SEL0=1'b0;
		#10

		IP3=1'b0;
		IP2=1'b0;
		IP1=1'b0;
		IP0=1'b0;	
		SEL1=1'b1;
		SEL0=1'b1;
		#10
		IP3=1'b0;
		IP2=1'b0;
		IP1=1'b0;
		IP0=1'b1;		
		SEL1=1'b1;
		SEL0=1'b1;
		#10
		IP3=1'b0;
		IP2=1'b0;
		IP1=1'b1;
		IP0=1'b0;		
		SEL1=1'b1;
		SEL0=1'b1;
		#10
		IP3=1'b0;
		IP2=1'b0;
		IP1=1'b1;
		IP0=1'b1;		
		SEL1=1'b1;
		SEL0=1'b1;
		#10
		IP3=1'b0;
		IP2=1'b1;
		IP1=1'b0;
		IP0=1'b0;	
		SEL1=1'b1;
		SEL0=1'b1;
		#10
		IP3=1'b0;
		IP2=1'b1;
		IP1=1'b0;
		IP0=1'b1;		
		SEL1=1'b1;
		SEL0=1'b1;
		#10
		IP3=1'b0;
		IP2=1'b1;
		IP1=1'b1;
		IP0=1'b0;		
		SEL1=1'b1;
		SEL0=1'b1;
		#10
		IP3=1'b0;
		IP2=1'b1;
		IP1=1'b1;
		IP0=1'b1;		
		SEL1=1'b1;
		SEL0=1'b1;
		#10
		IP3=1'b1;
		IP2=1'b0;
		IP1=1'b0;
		IP0=1'b0;	
		SEL1=1'b1;
		SEL0=1'b1;
		#10
		IP3=1'b1;
		IP2=1'b0;
		IP1=1'b0;
		IP0=1'b1;		
		SEL1=1'b1;
		SEL0=1'b1;
		#10
		IP3=1'b1;
		IP2=1'b0;
		IP1=1'b1;
		IP0=1'b0;		
		SEL1=1'b1;
		SEL0=1'b1;
		#10
		IP3=1'b1;
		IP2=1'b0;
		IP1=1'b1;
		IP0=1'b1;		
		SEL1=1'b1;
		SEL0=1'b1;
		#10
		IP3=1'b1;
		IP2=1'b1;
		IP1=1'b0;
		IP0=1'b0;	
		SEL1=1'b1;
		SEL0=1'b1;
		#10
		IP3=1'b1;
		IP2=1'b1;
		IP1=1'b0;
		IP0=1'b1;		
		SEL1=1'b1;
		SEL0=1'b1;
		#10
		IP3=1'b1;
		IP2=1'b1;
		IP1=1'b1;
		IP0=1'b0;		
		SEL1=1'b1;
		SEL0=1'b1;
		#10
		IP3=1'b1;
		IP2=1'b1;
		IP1=1'b1;
		IP0=1'b1;		
		SEL1=1'b1;
		SEL0=1'b1;
		#10;		
	
end

endmodule

Shift_Reg/shift.vcd
$date
	Mon Mar 19 19:09:10 2018
$end
$version
	Icarus Verilog
$end
$timescale
	1s
$end
$scope module testbench $end
$var wire 1 ! OP0 $end
$var wire 1 " OP1 $end
$var wire 1 # OP2 $end
$var wire 1 $ OP3 $end
$var reg 1 % IP0 $end
$var reg 1 & IP1 $end
$var reg 1 ' IP2 $end
$var reg 1 ( IP3 $end
$var reg 1 ) SEL0 $end
$var reg 1 * SEL1 $end
$scope module f1 $end
$var wire 1 + IP0 $end
$var wire 1 , IP1 $end
$var wire 1 - IP2 $end
$var wire 1 . IP3 $end
$var wire 1 ! OP0 $end
$var wire 1 " OP1 $end
$var wire 1 # OP2 $end
$var wire 1 $ OP3 $end
$var wire 1 / SEL0 $end
$var wire 1 0 SEL1 $end
$scope module m0 $end
$var wire 1 + i0 $end
$var wire 1 1 i1 $end
$var wire 1 , i2 $end
$var wire 1 , i3 $end
$var wire 1 2 n_s0 $end
$var wire 1 3 n_s1 $end
$var wire 1 ! out $end
$var wire 1 / s0 $end
$var wire 1 0 s1 $end
$var wire 1 4 t0 $end
$var wire 1 5 t1 $end
$var wire 1 6 t2 $end
$var wire 1 7 t3 $end
$upscope $end
$scope module m1 $end
$var wire 1 , i0 $end
$var wire 1 + i1 $end
$var wire 1 - i2 $end
$var wire 1 - i3 $end
$var wire 1 8 n_s0 $end
$var wire 1 9 n_s1 $end
$var wire 1 " out $end
$var wire 1 / s0 $end
$var wire 1 0 s1 $end
$var wire 1 : t0 $end
$var wire 1 ; t1 $end
$var wire 1 < t2 $end
$var wire 1 = t3 $end
$upscope $end
$scope module m2 $end
$var wire 1 - i0 $end
$var wire 1 , i1 $end
$var wire 1 . i2 $end
$var wire 1 . i3 $end
$var wire 1 > n_s0 $end
$var wire 1 ? n_s1 $end
$var wire 1 # out $end
$var wire 1 / s0 $end
$var wire 1 0 s1 $end
$var wire 1 @ t0 $end
$var wire 1 A t1 $end
$var wire 1 B t2 $end
$var wire 1 C t3 $end
$upscope $end
$scope module m3 $end
$var wire 1 . i0 $end
$var wire 1 - i1 $end
$var wire 1 D i2 $end
$var wire 1 + i3 $end
$var wire 1 E n_s0 $end
$var wire 1 F n_s1 $end
$var wire 1 $ out $end
$var wire 1 / s0 $end
$var wire 1 0 s1 $end
$var wire 1 G t0 $end
$var wire 1 H t1 $end
$var wire 1 I t2 $end
$var wire 1 J t3 $end
$upscope $end
$upscope $end
$upscope $end
$enddefinitions $end
#0
$dumpvars
0J
0I
0H
0G
1F
1E
1D
0C
0B
0A
0@
1?
1>
0=
0<
0;
0:
19
18
07
06
05
04
13
12
11
00
0/
0.
0-
0,
0+
0*
0)
0(
0'
0&
0%
0$
0#
0"
0!
$end
#10
1!
14
1%
1+
#20
0!
1"
04
1:
0%
0+
1&
1,
#30
1!
14
1%
1+
#40
0!
0"
1#
04
0:
1@
0%
0+
0&
0,
1'
1-
#50
1!
14
1%
1+
#60
0!
1"
04
1:
0%
0+
1&
1,
#70
1!
14
1%
1+
#80
0!
0"
0#
1$
04
0:
0@
1G
0%
0+
0&
0,
0'
0-
1(
1.
#90
1!
14
1%
1+
#100
0!
1"
04
1:
0%
0+
1&
1,
#110
1!
14
1%
1+
#120
0!
0"
1#
04
0:
1@
0%
0+
0&
0,
1'
1-
#130
1!
14
1%
1+
#140
0!
1"
04
1:
0%
0+
1&
1,
#150
1!
14
1%
1+
#160
0"
0#
0$
02
15
08
0>
0E
04
0:
0@
0G
1)
1/
0%
0+
0&
0,
0'
0-
0(
0.
#170
1"
1;
1%
1+
#180
0"
1#
0;
1A
0%
0+
1&
1,
#190
1"
1;
1%
1+
#200
0"
0#
1$
0;
0A
1H
0%
0+
0&
0,
1'
1-
#210
1"
1;
1%
1+
#220
0"
1#
0;
1A
0%
0+
1&
1,
#230
1"
1;
1%
1+
#240
0"
0#
0$
0;
0A
0H
0%
0+
0&
0,
0'
0-
1(
1.
#250
1"
1;
1%
1+
#260
0"
1#
0;
1A
0%
0+
1&
1,
#270
1"
1;
1%
1+
#280
0"
0#
1$
0;
0A
1H
0%
0+
0&
0,
1'
1-
#290
1"
1;
1%
1+
#300
0"
1#
0;
1A
0%
0+
1&
1,
#310
1"
1;
1%
1+
#320
0!
1I
0"
0#
1$
12
05
18
1>
1E
03
09
0?
0F
0;
0A
0H
0)
0/
1*
10
0%
0+
0&
0,
0'
0-
0(
0.
#330
1%
1+
#340
1!
16
0%
0+
1&
1,
#350
1%
1+
#360
0!
1"
06
1<
0%
0+
0&
0,
1'
1-
#370
1%
1+
#380
1!
16
0%
0+
1&
1,
#390
1%
1+
#400
0!
0"
1#
06
0<
1B
0%
0+
0&
0,
0'
0-
1(
1.
#410
1%
1+
#420
1!
16
0%
0+
1&
1,
#430
1%
1+
#440
0!
1"
06
1<
0%
0+
0&
0,
1'
1-
#450
1%
1+
#460
1!
16
0%
0+
1&
1,
#470
1%
1+
#480
0$
0I
0!
0"
0#
02
08
0>
0E
06
0<
0B
1)
1/
0%
0+
0&
0,
0'
0-
0(
0.
#490
1$
1J
1%
1+
#500
0$
1!
0J
17
0%
0+
1&
1,
#510
1$
1J
1%
1+
#520
0$
0!
1"
0J
07
1=
0%
0+
0&
0,
1'
1-
#530
1$
1J
1%
1+
#540
0$
1!
0J
17
0%
0+
1&
1,
#550
1$
1J
1%
1+
#560
0$
0!
0"
1#
0J
07
0=
1C
0%
0+
0&
0,
0'
0-
1(
1.
#570
1$
1J
1%
1+
#580
0$
1!
0J
17
0%
0+
1&
1,
#590
1$
1J
1%
1+
#600
0$
0!
1"
0J
07
1=
0%
0+
0&
0,
1'
1-
#610
1$
1J
1%
1+
#620
0$
1!
0J
17
0%
0+
1&
1,
#630
1$
1J
1%
1+
