Johnson's_Counter/johnson.v
module johnson(clk,reset,count);

input clk,reset;

output [3:0] count; 

reg[3:0] count;
reg [3:0] counter;

always @(posedge clk )

begin
  if (reset)
    assign counter=4'd0;
  else if(counter==4'b1111)
    begin
    assign counter=counter<<1;
    assign counter=counter+4'd0;
    end
else if(counter==4'b1000)
    begin
    assign counter=counter<<1;
    assign counter=counter+4'd0;
    end
else if(counter==4'b1100)
    begin
    assign counter=counter<<1;
    assign counter=counter+4'd0;
    end
else if(counter==4'b1110)
    begin
    assign counter=counter<<1;
    assign counter=counter+4'd0;
    end
  else
    begin
    assign counter=counter<<1;
    assign counter=counter+4'd1;
    end
assign count=counter;

end

endmodule

module testbench();

reg clk=0;
reg reset;

wire[3:0] count;

integer i;
johnson f1(.clk(clk),.count(count),.reset(reset));

always #1 clk=~clk;

initial 
begin

$monitor("count = %b",count);
$dumpfile("johnson.vcd");
$dumpvars;

reset=0;#1
reset=1;#1
reset=0;
#100 

$finish;

end

endmodule

Johnson's_Counter/johnson.vcd
$date
	Mon Mar 19 19:11:12 2018
$end
$version
	Icarus Verilog
$end
$timescale
	1s
$end
$scope module testbench $end
$var wire 4 ! count [3:0] $end
$var reg 1 " clk $end
$var reg 1 # reset $end
$scope module f1 $end
$var wire 1 $ clk $end
$var wire 1 % reset $end
$var reg 4 & count [3:0] $end
$var reg 4 ' counter [3:0] $end
$upscope $end
$upscope $end
$enddefinitions $end
#0
$dumpvars
bx '
bx &
0%
0$
0#
0"
bx !
$end
#1
b0 &
b0 !
b0 '
1#
1%
1"
1$
#2
0#
0%
0"
0$
#3
b1 !
b1 '
b1 &
1"
1$
#4
0"
0$
#5
b11 '
b11 &
b11 !
1"
1$
#6
0"
0$
#7
b111 '
b111 &
b111 !
1"
1$
#8
0"
0$
#9
b1111 '
b1111 &
b1111 !
1"
1$
#10
0"
0$
#11
b1110 '
b1110 &
b1110 !
1"
1$
#12
0"
0$
#13
b1100 '
b1100 &
b1100 !
1"
1$
#14
0"
0$
#15
b1000 '
b1000 &
b1000 !
1"
1$
#16
0"
0$
#17
b0 '
b0 &
b0 !
1"
1$
#18
0"
0$
#19
b1 !
b1 '
b1 &
1"
1$
#20
0"
0$
#21
b11 '
b11 &
b11 !
1"
1$
#22
0"
0$
#23
b111 '
b111 &
b111 !
1"
1$
#24
0"
0$
#25
b1111 '
b1111 &
b1111 !
1"
1$
#26
0"
0$
#27
b1110 '
b1110 &
b1110 !
1"
1$
#28
0"
0$
#29
b1100 '
b1100 &
b1100 !
1"
1$
#30
0"
0$
#31
b1000 '
b1000 &
b1000 !
1"
1$
#32
0"
0$
#33
b0 '
b0 &
b0 !
1"
1$
#34
0"
0$
#35
b1 !
b1 '
b1 &
1"
1$
#36
0"
0$
#37
b11 '
b11 &
b11 !
1"
1$
#38
0"
0$
#39
b111 '
b111 &
b111 !
1"
1$
#40
0"
0$
#41
b1111 '
b1111 &
b1111 !
1"
1$
#42
0"
0$
#43
b1110 '
b1110 &
b1110 !
1"
1$
#44
0"
0$
#45
b1100 '
b1100 &
b1100 !
1"
1$
#46
0"
0$
#47
b1000 '
b1000 &
b1000 !
1"
1$
#48
0"
0$
#49
b0 '
b0 &
b0 !
1"
1$
#50
0"
0$
#51
b1 !
b1 '
b1 &
1"
1$
#52
0"
0$
#53
b11 '
b11 &
b11 !
1"
1$
#54
0"
0$
#55
b111 '
b111 &
b111 !
1"
1$
#56
0"
0$
#57
b1111 '
b1111 &
b1111 !
1"
1$
#58
0"
0$
#59
b1110 '
b1110 &
b1110 !
1"
1$
#60
0"
0$
#61
b1100 '
b1100 &
b1100 !
1"
1$
#62
0"
0$
#63
b1000 '
b1000 &
b1000 !
1"
1$
#64
0"
0$
#65
b0 '
b0 &
b0 !
1"
1$
#66
0"
0$
#67
b1 !
b1 '
b1 &
1"
1$
#68
0"
0$
#69
b11 '
b11 &
b11 !
1"
1$
#70
0"
0$
#71
b111 '
b111 &
b111 !
1"
1$
#72
0"
0$
#73
b1111 '
b1111 &
b1111 !
1"
1$
#74
0"
0$
#75
b1110 '
b1110 &
b1110 !
1"
1$
#76
0"
0$
#77
b1100 '
b1100 &
b1100 !
1"
1$
#78
0"
0$
#79
b1000 '
b1000 &
b1000 !
1"
1$
#80
0"
0$
#81
b0 '
b0 &
b0 !
1"
1$
#82
0"
0$
#83
b1 !
b1 '
b1 &
1"
1$
#84
0"
0$
#85
b11 '
b11 &
b11 !
1"
1$
#86
0"
0$
#87
b111 '
b111 &
b111 !
1"
1$
#88
0"
0$
#89
b1111 '
b1111 &
b1111 !
1"
1$
#90
0"
0$
#91
b1110 '
b1110 &
b1110 !
1"
1$
#92
0"
0$
#93
b1100 '
b1100 &
b1100 !
1"
1$
#94
0"
0$
#95
b1000 '
b1000 &
b1000 !
1"
1$
#96
0"
0$
#97
b0 '
b0 &
b0 !
1"
1$
#98
0"
0$
#99
b1 !
b1 '
b1 &
1"
1$
#100
0"
0$
#101
b11 '
b11 &
b11 !
1"
1$
