Flip-Flops/JK/jk.v
module JK(j,k,qb,q,t);
input j;
input k;
input qb;
output q;
output t;

wire q1,q2;

nand na1(q1,k,qb);
nand na2(q2,j,(~qb));
nand na3(t,q1,qb);
nand na4(q,q2,t);

endmodule

module testbench();
reg j,k,qb;
wire q,t;

JK f1(j,k,qb,q,t);

initial
begin

$monitor("Q[1] = %b : J = %b : K = %b : Q = %b : Q` = %b",qb,j,k,q,t);
$dumpfile("jk.vcd");
$dumpvars;

qb = 1'b0;
j = 1'b0 ; k = 1'b0 ; #5 
j = 1'b0 ; k = 1'b1 ; #5 
j = 1'b1 ; k = 1'b0 ; #5 
j = 1'b1 ; k = 1'b1 ; #5 
j = 1'b1 ; k = 1'b1 ; #5
qb = 1'b1;
j = 1'b0 ; k = 1'b0 ; #5 
j = 1'b0 ; k = 1'b1 ; #5 
j = 1'b1 ; k = 1'b0 ; #5 
j = 1'b1 ; k = 1'b1 ; #5 
j = 1'b1 ; k = 1'b1 ; #5
j = 1'b1 ; k = 1'b1 ;

end
endmodule

Flip-Flops/JK/jk.vcd
$date
	Mon Mar 19 19:08:02 2018
$end
$version
	Icarus Verilog
$end
$timescale
	1s
$end
$scope module testbench $end
$var wire 1 ! q $end
$var wire 1 " t $end
$var reg 1 # j $end
$var reg 1 $ k $end
$var reg 1 % qb $end
$scope module f1 $end
$var wire 1 & j $end
$var wire 1 ' k $end
$var wire 1 ! q $end
$var wire 1 ( q1 $end
$var wire 1 ) q2 $end
$var wire 1 * qb $end
$var wire 1 " t $end
$upscope $end
$upscope $end
$enddefinitions $end
#0
$dumpvars
0*
1)
1(
0'
0&
0%
0$
0#
1"
0!
$end
#5
1$
1'
#10
1!
0)
0$
0'
1#
1&
#15
1$
1'
#25
1)
0"
0$
0'
0#
0&
1%
1*
#30
0!
1"
0(
1$
1'
#35
1!
0"
1(
0$
0'
1#
1&
#40
0!
1"
0(
1$
1'
