Demux/demux.v
module demux(s0,s1,I,en,d0,d1,d2,d3);

input s0,s1,I,en;

output d0,d1,d2,d3;

assign d0=(~s0)&(~s1)& I& en;
assign d1=(~s0)& s1& I& en;
assign d2=s0&(~s1)& I & en;
assign d3=s0& s1 & I & en;

endmodule

module testbench();

reg s0,s1,I,en;
wire d0,d1,d2,d3;
demux aa (.d0(d0),.d1(d1),.d2(d2),.d3(d3),.I(I),.en(en),.s1(s0),.s0(s1));

initial begin

$monitor("d0 = %b  : d1 = %b  : d2 =  %b  : d3 = %b  : s1 = %b  : s2 = %b  : en = %b  : I = %b",d0,d1,d2,d3,s1,s0,en,I);
$dumpfile("demux.vcd");
$dumpvars;


I=1'b1;en=1'b0;s1=1'b0;s0=1'b0;
#1
I=1'b1;en=1'b0;s1=1'b0;s0=1'b1;
#1
I=1'b1;en=1'b0;s1=1'b1;s0=1'b0;
#1
I=1'b1;en=1'b0;s1=1'b1;s0=1'b1;
#1
I=1'b0;en=1'b0;s1=1'b0;s0=1'b0;
#1
I=1'b0;en=1'b0;s1=1'b0;s0=1'b1;
#1
I=1'b0;en=1'b0;s1=1'b1;s0=1'b0;
#1
I=1'b0;en=1'b0;s1=1'b1;s0=1'b1;
#1
I=1'b1;en=1'b1;s1=1'b0;s0=1'b0;
#1
I=1'b1;en=1'b1;s1=1'b0;s0=1'b1;
#1
I=1'b1;en=1'b1;s1=1'b1;s0=1'b0;
#1
I=1'b1;en=1'b1;s1=1'b1;s0=1'b1;
#1
I=1'b0;en=1'b1;s1=1'b0;s0=1'b0;
#1
I=1'b0;en=1'b1;s1=1'b0;s0=1'b1;
#1
I=1'b0;en=1'b1;s1=1'b1;s0=1'b0;
#1
I=1'b0;en=1'b1;s1=1'b1;s0=1'b1;

end

endmodule

Demux/demux.vcd
$date
	Mon Mar 19 19:04:34 2018
$end
$version
	Icarus Verilog
$end
$timescale
	1s
$end
$scope module testbench $end
$var wire 1 ! d0 $end
$var wire 1 " d1 $end
$var wire 1 # d2 $end
$var wire 1 $ d3 $end
$var reg 1 % I $end
$var reg 1 & en $end
$var reg 1 ' s0 $end
$var reg 1 ( s1 $end
$scope module aa $end
$var wire 1 ) I $end
$var wire 1 ! d0 $end
$var wire 1 " d1 $end
$var wire 1 # d2 $end
$var wire 1 $ d3 $end
$var wire 1 * en $end
$var wire 1 + s0 $end
$var wire 1 , s1 $end
$upscope $end
$upscope $end
$enddefinitions $end
#0
$dumpvars
0,
0+
0*
1)
0(
0'
0&
1%
0$
0#
0"
0!
$end
#1
1'
1,
#2
0'
0,
1(
1+
#3
1'
1,
#4
0'
0,
0(
0+
0%
0)
#5
1'
1,
#6
0'
0,
1(
1+
#7
1'
1,
#8
1!
0$
0'
0,
0(
0+
1&
1*
1%
1)
#9
0!
1"
1'
1,
#10
1#
0"
0'
0,
1(
1+
#11
0#
1$
1'
1,
#12
0$
0'
0,
0(
0+
0%
0)
#13
1'
1,
#14
0'
0,
1(
1+
#15
1'
1,
