Flip-Flops/SR/sr.v
module SR(s,r,qb,q,t);
input s;
input r;
input qb;
output q;
output t;

wire q1,q2;
nand na1(q1,s);
nand na2(q2,r);
nand na4(t,q2,qb);
nand na3(q,q1,t);


endmodule

module testbench();
reg s,r,qb;
wire q,t;

SR f1(s,r,qb,q,t);

initial
begin

$monitor("S = %b : R = %b : Q[1] =%b : Q = %b : Q` = %b",s,r,qb,q,t);
$dumpfile("sr.vcd");
$dumpvars;
qb = 1'b0;
s = 1'b0 ; r = 1'b0 ; #5 
s = 1'b0 ; r = 1'b1 ; #5 
s = 1'b1 ; r = 1'b0 ; #5 
s = 1'b1 ; r = 1'b1 ; #5 
s = 1'b1 ; r = 1'b1 ; #5
qb = 1'b1;
s = 1'b0 ; r = 1'b0 ; #5 
s = 1'b0 ; r = 1'b1 ; #5 
s = 1'b1 ; r = 1'b0 ; #5 
s = 1'b1 ; r = 1'b1 ; #5 
s = 1'b1 ; r = 1'b1 ; #5
s = 1'b1 ; r = 1'b1 ;
end
endmodule

Flip-Flops/SR/sr.vcd
$date
	Mon Mar 19 19:08:19 2018
$end
$version
	Icarus Verilog
$end
$timescale
	1s
$end
$scope module testbench $end
$var wire 1 ! q $end
$var wire 1 " t $end
$var reg 1 # qb $end
$var reg 1 $ r $end
$var reg 1 % s $end
$scope module f1 $end
$var wire 1 ! q $end
$var wire 1 & q1 $end
$var wire 1 ' q2 $end
$var wire 1 ( qb $end
$var wire 1 ) r $end
$var wire 1 * s $end
$var wire 1 " t $end
$upscope $end
$upscope $end
$enddefinitions $end
#0
$dumpvars
0*
0)
0(
1'
1&
0%
0$
0#
1"
0!
$end
#5
0'
1$
1)
#10
1!
1'
0&
0$
0)
1%
1*
#15
0'
1$
1)
#25
0"
1!
1'
1&
0$
0)
0%
0*
1#
1(
#30
0!
1"
0'
1$
1)
#35
0"
1!
1'
0&
0$
0)
1%
1*
#40
1"
0'
1$
1)
