Up_Down_Counter/updown.v
module updowncountermod(clk, clear, updown, q);

input clk;

input clear;

input updown;

output [3:0] q;

reg [3:0] q;

always@(posedge clear or posedge clk)

begin

if(clear)

q <=4'b0000;

else if(updown)

q <= q+1'b1;

else

q <= q-1'b1;

end

 

endmodule

module updowncountert_b;

reg clk;

reg clear;

reg updown;

wire [3:0] q;

updowncountermod uut (.clk(clk),.clear(clear), .updown(updown), .q(q)   );

initial begin

$monitor("Clock = %b : Clear = %b : Updown = %b : Q = %b",clk,clear,updown,q);
$dumpfile("updown.vcd");
$dumpvars;

clk = 0;

clear = 0;

updown = 0;

 

#5 clear=1'b1;

#5 clear=1'b0;

#100 updown=1'b1;

end

always #5 clk=~clk;

initial #150 $finish;

endmodule

Up_Down_Counter/updown.vcd
$date
	Mon Mar 19 19:34:50 2018
$end
$version
	Icarus Verilog
$end
$timescale
	1s
$end
$scope module updowncountert_b $end
$var wire 4 ! q [3:0] $end
$var reg 1 " clear $end
$var reg 1 # clk $end
$var reg 1 $ updown $end
$scope module uut $end
$var wire 1 % clear $end
$var wire 1 & clk $end
$var wire 1 ' updown $end
$var reg 4 ( q [3:0] $end
$upscope $end
$upscope $end
$enddefinitions $end
#0
$dumpvars
bx (
0'
0&
0%
0$
0#
0"
bx !
$end
#5
b0 (
b0 !
1#
1&
1"
1%
#10
0#
0&
0"
0%
#15
b1111 (
b1111 !
1#
1&
#20
0#
0&
#25
b1110 (
b1110 !
1#
1&
#30
0#
0&
#35
b1101 (
b1101 !
1#
1&
#40
0#
0&
#45
b1100 (
b1100 !
1#
1&
#50
0#
0&
#55
b1011 (
b1011 !
1#
1&
#60
0#
0&
#65
b1010 (
b1010 !
1#
1&
#70
0#
0&
#75
b1001 (
b1001 !
1#
1&
#80
0#
0&
#85
b1000 (
b1000 !
1#
1&
#90
0#
0&
#95
b111 (
b111 !
1#
1&
#100
0#
0&
#105
b110 (
b110 !
1#
1&
#110
0#
0&
1$
1'
#115
b111 (
b111 !
1#
1&
#120
0#
0&
#125
b1000 (
b1000 !
1#
1&
#130
0#
0&
#135
b1001 (
b1001 !
1#
1&
#140
0#
0&
#145
b1010 (
b1010 !
1#
1&
