4-Bit_Adder/4bitadder.v
module full_adder(a,b,cin,sum,cout);
input a;
input b;
input cin;
output sum;
output cout;

assign sum = a^b^cin;
assign cout = (a & b) | (cin & (a^b)); 

endmodule

module bitadder(A,B,Cin,Sum,Cout);

input [3:0]A;
input [3:0]B;
input Cin;

output [3:0]Sum;
output Cout;

wire c1,c2,c3;

full_adder f1(.a(A[0]),.b(B[0]),.cin(Cin),.sum(Sum[0]),.cout(c1));
full_adder f2(.a(A[1]),.b(B[1]),.cin(c1),.sum(Sum[1]),.cout(c2));
full_adder f3(.a(A[2]),.b(B[2]),.cin(c2),.sum(Sum[2]),.cout(c3));
full_adder f4(.a(A[3]),.b(B[3]),.cin(c3),.sum(Sum[3]),.cout(Cout));

endmodule

module testbench();
reg [3:0]A;
reg [3:0]B;
reg Cin;
wire [3:0]Sum;
wire Cout;

bitadder tb(A,B,Cin,Sum,Cout);

initial
begin

$monitor("A = %b : B = %b : Cin = %b : Sum = %b : Cout = %b ",A,B,Cin,Sum,Cout);
$dumpfile("4bitadder.vcd");
$dumpvars;

A = 4'b0000 ; B = 4'b0000 ; Cin = 1'b0 ;
#5; 
A = 4'b0000 ; B = 4'b0001 ; Cin = 1'b0 ;
#5; 
A = 4'b0000 ; B = 4'b0010 ; Cin = 1'b0 ;
#5; 
A = 4'b0000 ; B = 4'b0011 ; Cin = 1'b0 ;
#5; 
A = 4'b0000 ; B = 4'b0100 ; Cin = 1'b0 ;
#5; 
A = 4'b0000 ; B = 4'b0101 ; Cin = 1'b0 ;
#5; 
A = 4'b0000 ; B = 4'b0110 ; Cin = 1'b0 ;
#5; 
A = 4'b0000 ; B = 4'b0111 ; Cin = 1'b0 ;
#5; 
A = 4'b0000 ; B = 4'b1000 ; Cin = 1'b0 ;
#5; 
A = 4'b0000 ; B = 4'b1001 ; Cin = 1'b0 ;
#5; 
A = 4'b0000 ; B = 4'b1010 ; Cin = 1'b0 ;
#5; 
A = 4'b0000 ; B = 4'b1011 ; Cin = 1'b0 ;
#5; 
A = 4'b0000 ; B = 4'b1100 ; Cin = 1'b0 ;
#5; 
A = 4'b0000 ; B = 4'b1101 ; Cin = 1'b0 ;
#5; 
A = 4'b0000 ; B = 4'b1110 ; Cin = 1'b0 ;
#5; 
A = 4'b0000 ; B = 4'b1111 ; Cin = 1'b0 ;
#5; 
A = 4'b0001 ; B = 4'b0000 ; Cin = 1'b0 ;
#5; 
A = 4'b0001 ; B = 4'b0001 ; Cin = 1'b0 ;
#5; 
A = 4'b0001 ; B = 4'b0010 ; Cin = 1'b0 ;
#5; 
A = 4'b0001 ; B = 4'b0011 ; Cin = 1'b0 ;
#5; 
A = 4'b0001 ; B = 4'b0100 ; Cin = 1'b0 ;
#5; 
A = 4'b0001 ; B = 4'b0101 ; Cin = 1'b0 ;
#5; 
A = 4'b0001 ; B = 4'b0110 ; Cin = 1'b0 ;
#5; 
A = 4'b0001 ; B = 4'b0111 ; Cin = 1'b0 ;
#5; 
A = 4'b0001 ; B = 4'b1000 ; Cin = 1'b0 ;
#5; 
A = 4'b0001 ; B = 4'b1001 ; Cin = 1'b0 ;
#5; 
A = 4'b0001 ; B = 4'b1010 ; Cin = 1'b0 ;
#5; 
A = 4'b0001 ; B = 4'b1011 ; Cin = 1'b0 ;
#5; 
A = 4'b0001 ; B = 4'b1100 ; Cin = 1'b0 ;
#5; 
A = 4'b0001 ; B = 4'b1101 ; Cin = 1'b0 ;
#5; 
A = 4'b0001 ; B = 4'b1110 ; Cin = 1'b0 ;
#5; 
A = 4'b0001 ; B = 4'b1111 ; Cin = 1'b0 ;
#5; 
A = 4'b0010 ; B = 4'b0000 ; Cin = 1'b0 ;
#5; 
A = 4'b0010 ; B = 4'b0001 ; Cin = 1'b0 ;
#5; 
A = 4'b0010 ; B = 4'b0010 ; Cin = 1'b0 ;
#5; 
A = 4'b0010 ; B = 4'b0011 ; Cin = 1'b0 ;
#5; 
A = 4'b0010 ; B = 4'b0100 ; Cin = 1'b0 ;
#5; 
A = 4'b0010 ; B = 4'b0101 ; Cin = 1'b0 ;
#5; 
A = 4'b0010 ; B = 4'b0110 ; Cin = 1'b0 ;
#5; 
A = 4'b0010 ; B = 4'b0111 ; Cin = 1'b0 ;
#5; 
A = 4'b0010 ; B = 4'b1000 ; Cin = 1'b0 ;
#5; 
A = 4'b0010 ; B = 4'b1001 ; Cin = 1'b0 ;
#5; 
A = 4'b0010 ; B = 4'b1010 ; Cin = 1'b0 ;
#5; 
A = 4'b0010 ; B = 4'b1011 ; Cin = 1'b0 ;
#5; 
A = 4'b0010 ; B = 4'b1100 ; Cin = 1'b0 ;
#5; 
A = 4'b0010 ; B = 4'b1101 ; Cin = 1'b0 ;
#5; 
A = 4'b0010 ; B = 4'b1110 ; Cin = 1'b0 ;
#5; 
A = 4'b0010 ; B = 4'b1111 ; Cin = 1'b0 ;
#5; 
A = 4'b0011 ; B = 4'b0000 ; Cin = 1'b0 ;
#5; 
A = 4'b0011 ; B = 4'b0001 ; Cin = 1'b0 ;
#5; 
A = 4'b0011 ; B = 4'b0010 ; Cin = 1'b0 ;
#5; 
A = 4'b0011 ; B = 4'b0011 ; Cin = 1'b0 ;
#5; 
A = 4'b0011 ; B = 4'b0100 ; Cin = 1'b0 ;
#5; 
A = 4'b0011 ; B = 4'b0101 ; Cin = 1'b0 ;
#5; 
A = 4'b0011 ; B = 4'b0110 ; Cin = 1'b0 ;
#5; 
A = 4'b0011 ; B = 4'b0111 ; Cin = 1'b0 ;
#5; 
A = 4'b0011 ; B = 4'b1000 ; Cin = 1'b0 ;
#5; 
A = 4'b0011 ; B = 4'b1001 ; Cin = 1'b0 ;
#5; 
A = 4'b0011 ; B = 4'b1010 ; Cin = 1'b0 ;
#5; 
A = 4'b0011 ; B = 4'b1011 ; Cin = 1'b0 ;
#5; 
A = 4'b0011 ; B = 4'b1100 ; Cin = 1'b0 ;
#5; 
A = 4'b0011 ; B = 4'b1101 ; Cin = 1'b0 ;
#5; 
A = 4'b0011 ; B = 4'b1110 ; Cin = 1'b0 ;
#5; 
A = 4'b0011 ; B = 4'b1111 ; Cin = 1'b0 ;
#5; 
A = 4'b0100 ; B = 4'b0000 ; Cin = 1'b0 ;
#5; 
A = 4'b0100 ; B = 4'b0001 ; Cin = 1'b0 ;
#5; 
A = 4'b0100 ; B = 4'b0010 ; Cin = 1'b0 ;
#5; 
A = 4'b0100 ; B = 4'b0011 ; Cin = 1'b0 ;
#5; 
A = 4'b0100 ; B = 4'b0100 ; Cin = 1'b0 ;
#5; 
A = 4'b0100 ; B = 4'b0101 ; Cin = 1'b0 ;
#5; 
A = 4'b0100 ; B = 4'b0110 ; Cin = 1'b0 ;
#5; 
A = 4'b0100 ; B = 4'b0111 ; Cin = 1'b0 ;
#5; 
A = 4'b0100 ; B = 4'b1000 ; Cin = 1'b0 ;
#5; 
A = 4'b0100 ; B = 4'b1001 ; Cin = 1'b0 ;
#5; 
A = 4'b0100 ; B = 4'b1010 ; Cin = 1'b0 ;
#5; 
A = 4'b0100 ; B = 4'b1011 ; Cin = 1'b0 ;
#5; 
A = 4'b0100 ; B = 4'b1100 ; Cin = 1'b0 ;
#5; 
A = 4'b0100 ; B = 4'b1101 ; Cin = 1'b0 ;
#5; 
A = 4'b0100 ; B = 4'b1110 ; Cin = 1'b0 ;
#5; 
A = 4'b0100 ; B = 4'b1111 ; Cin = 1'b0 ;
#5; 
A = 4'b0101 ; B = 4'b0000 ; Cin = 1'b0 ;
#5; 
A = 4'b0101 ; B = 4'b0001 ; Cin = 1'b0 ;
#5; 
A = 4'b0101 ; B = 4'b0010 ; Cin = 1'b0 ;
#5; 
A = 4'b0101 ; B = 4'b0011 ; Cin = 1'b0 ;
#5; 
A = 4'b0101 ; B = 4'b0100 ; Cin = 1'b0 ;
#5; 
A = 4'b0101 ; B = 4'b0101 ; Cin = 1'b0 ;
#5; 
A = 4'b0101 ; B = 4'b0110 ; Cin = 1'b0 ;
#5; 
A = 4'b0101 ; B = 4'b0111 ; Cin = 1'b0 ;
#5; 
A = 4'b0101 ; B = 4'b1000 ; Cin = 1'b0 ;
#5; 
A = 4'b0101 ; B = 4'b1001 ; Cin = 1'b0 ;
#5; 
A = 4'b0101 ; B = 4'b1010 ; Cin = 1'b0 ;
#5; 
A = 4'b0101 ; B = 4'b1011 ; Cin = 1'b0 ;
#5; 
A = 4'b0101 ; B = 4'b1100 ; Cin = 1'b0 ;
#5; 
A = 4'b0101 ; B = 4'b1101 ; Cin = 1'b0 ;
#5; 
A = 4'b0101 ; B = 4'b1110 ; Cin = 1'b0 ;
#5; 
A = 4'b0101 ; B = 4'b1111 ; Cin = 1'b0 ;
#5; 
A = 4'b0110 ; B = 4'b0000 ; Cin = 1'b0 ;
#5; 
A = 4'b0110 ; B = 4'b0001 ; Cin = 1'b0 ;
#5; 
A = 4'b0110 ; B = 4'b0010 ; Cin = 1'b0 ;
#5; 
A = 4'b0110 ; B = 4'b0011 ; Cin = 1'b0 ;
#5; 
A = 4'b0110 ; B = 4'b0100 ; Cin = 1'b0 ;
#5; 
A = 4'b0110 ; B = 4'b0101 ; Cin = 1'b0 ;
#5; 
A = 4'b0110 ; B = 4'b0110 ; Cin = 1'b0 ;
#5; 
A = 4'b0110 ; B = 4'b0111 ; Cin = 1'b0 ;
#5; 
A = 4'b0110 ; B = 4'b1000 ; Cin = 1'b0 ;
#5; 
A = 4'b0110 ; B = 4'b1001 ; Cin = 1'b0 ;
#5; 
A = 4'b0110 ; B = 4'b1010 ; Cin = 1'b0 ;
#5; 
A = 4'b0110 ; B = 4'b1011 ; Cin = 1'b0 ;
#5; 
A = 4'b0110 ; B = 4'b1100 ; Cin = 1'b0 ;
#5; 
A = 4'b0110 ; B = 4'b1101 ; Cin = 1'b0 ;
#5; 
A = 4'b0110 ; B = 4'b1110 ; Cin = 1'b0 ;
#5; 
A = 4'b0110 ; B = 4'b1111 ; Cin = 1'b0 ;
#5; 
A = 4'b0111 ; B = 4'b0000 ; Cin = 1'b0 ;
#5; 
A = 4'b0111 ; B = 4'b0001 ; Cin = 1'b0 ;
#5; 
A = 4'b0111 ; B = 4'b0010 ; Cin = 1'b0 ;
#5; 
A = 4'b0111 ; B = 4'b0011 ; Cin = 1'b0 ;
#5; 
A = 4'b0111 ; B = 4'b0100 ; Cin = 1'b0 ;
#5; 
A = 4'b0111 ; B = 4'b0101 ; Cin = 1'b0 ;
#5; 
A = 4'b0111 ; B = 4'b0110 ; Cin = 1'b0 ;
#5; 
A = 4'b0111 ; B = 4'b0111 ; Cin = 1'b0 ;
#5; 
A = 4'b0111 ; B = 4'b1000 ; Cin = 1'b0 ;
#5; 
A = 4'b0111 ; B = 4'b1001 ; Cin = 1'b0 ;
#5; 
A = 4'b0111 ; B = 4'b1010 ; Cin = 1'b0 ;
#5; 
A = 4'b0111 ; B = 4'b1011 ; Cin = 1'b0 ;
#5; 
A = 4'b0111 ; B = 4'b1100 ; Cin = 1'b0 ;
#5; 
A = 4'b0111 ; B = 4'b1101 ; Cin = 1'b0 ;
#5; 
A = 4'b0111 ; B = 4'b1110 ; Cin = 1'b0 ;
#5; 
A = 4'b0111 ; B = 4'b1111 ; Cin = 1'b0 ;
#5; 
A = 4'b1000 ; B = 4'b0000 ; Cin = 1'b0 ;
#5; 
A = 4'b1000 ; B = 4'b0001 ; Cin = 1'b0 ;
#5; 
A = 4'b1000 ; B = 4'b0010 ; Cin = 1'b0 ;
#5; 
A = 4'b1000 ; B = 4'b0011 ; Cin = 1'b0 ;
#5; 
A = 4'b1000 ; B = 4'b0100 ; Cin = 1'b0 ;
#5; 
A = 4'b1000 ; B = 4'b0101 ; Cin = 1'b0 ;
#5; 
A = 4'b1000 ; B = 4'b0110 ; Cin = 1'b0 ;
#5; 
A = 4'b1000 ; B = 4'b0111 ; Cin = 1'b0 ;
#5; 
A = 4'b1000 ; B = 4'b1000 ; Cin = 1'b0 ;
#5; 
A = 4'b1000 ; B = 4'b1001 ; Cin = 1'b0 ;
#5; 
A = 4'b1000 ; B = 4'b1010 ; Cin = 1'b0 ;
#5; 
A = 4'b1000 ; B = 4'b1011 ; Cin = 1'b0 ;
#5; 
A = 4'b1000 ; B = 4'b1100 ; Cin = 1'b0 ;
#5; 
A = 4'b1000 ; B = 4'b1101 ; Cin = 1'b0 ;
#5; 
A = 4'b1000 ; B = 4'b1110 ; Cin = 1'b0 ;
#5; 
A = 4'b1000 ; B = 4'b1111 ; Cin = 1'b0 ;
#5; 
A = 4'b1001 ; B = 4'b0000 ; Cin = 1'b0 ;
#5; 
A = 4'b1001 ; B = 4'b0001 ; Cin = 1'b0 ;
#5; 
A = 4'b1001 ; B = 4'b0010 ; Cin = 1'b0 ;
#5; 
A = 4'b1001 ; B = 4'b0011 ; Cin = 1'b0 ;
#5; 
A = 4'b1001 ; B = 4'b0100 ; Cin = 1'b0 ;
#5; 
A = 4'b1001 ; B = 4'b0101 ; Cin = 1'b0 ;
#5; 
A = 4'b1001 ; B = 4'b0110 ; Cin = 1'b0 ;
#5; 
A = 4'b1001 ; B = 4'b0111 ; Cin = 1'b0 ;
#5; 
A = 4'b1001 ; B = 4'b1000 ; Cin = 1'b0 ;
#5; 
A = 4'b1001 ; B = 4'b1001 ; Cin = 1'b0 ;
#5; 
A = 4'b1001 ; B = 4'b1010 ; Cin = 1'b0 ;
#5; 
A = 4'b1001 ; B = 4'b1011 ; Cin = 1'b0 ;
#5; 
A = 4'b1001 ; B = 4'b1100 ; Cin = 1'b0 ;
#5; 
A = 4'b1001 ; B = 4'b1101 ; Cin = 1'b0 ;
#5; 
A = 4'b1001 ; B = 4'b1110 ; Cin = 1'b0 ;
#5; 
A = 4'b1001 ; B = 4'b1111 ; Cin = 1'b0 ;
#5; 
A = 4'b1010 ; B = 4'b0000 ; Cin = 1'b0 ;
#5; 
A = 4'b1010 ; B = 4'b0001 ; Cin = 1'b0 ;
#5; 
A = 4'b1010 ; B = 4'b0010 ; Cin = 1'b0 ;
#5; 
A = 4'b1010 ; B = 4'b0011 ; Cin = 1'b0 ;
#5; 
A = 4'b1010 ; B = 4'b0100 ; Cin = 1'b0 ;
#5; 
A = 4'b1010 ; B = 4'b0101 ; Cin = 1'b0 ;
#5; 
A = 4'b1010 ; B = 4'b0110 ; Cin = 1'b0 ;
#5; 
A = 4'b1010 ; B = 4'b0111 ; Cin = 1'b0 ;
#5; 
A = 4'b1010 ; B = 4'b1000 ; Cin = 1'b0 ;
#5; 
A = 4'b1010 ; B = 4'b1001 ; Cin = 1'b0 ;
#5; 
A = 4'b1010 ; B = 4'b1010 ; Cin = 1'b0 ;
#5; 
A = 4'b1010 ; B = 4'b1011 ; Cin = 1'b0 ;
#5; 
A = 4'b1010 ; B = 4'b1100 ; Cin = 1'b0 ;
#5; 
A = 4'b1010 ; B = 4'b1101 ; Cin = 1'b0 ;
#5; 
A = 4'b1010 ; B = 4'b1110 ; Cin = 1'b0 ;
#5; 
A = 4'b1010 ; B = 4'b1111 ; Cin = 1'b0 ;
#5; 
A = 4'b1011 ; B = 4'b0000 ; Cin = 1'b0 ;
#5; 
A = 4'b1011 ; B = 4'b0001 ; Cin = 1'b0 ;
#5; 
A = 4'b1011 ; B = 4'b0010 ; Cin = 1'b0 ;
#5; 
A = 4'b1011 ; B = 4'b0011 ; Cin = 1'b0 ;
#5; 
A = 4'b1011 ; B = 4'b0100 ; Cin = 1'b0 ;
#5; 
A = 4'b1011 ; B = 4'b0101 ; Cin = 1'b0 ;
#5; 
A = 4'b1011 ; B = 4'b0110 ; Cin = 1'b0 ;
#5; 
A = 4'b1011 ; B = 4'b0111 ; Cin = 1'b0 ;
#5; 
A = 4'b1011 ; B = 4'b1000 ; Cin = 1'b0 ;
#5; 
A = 4'b1011 ; B = 4'b1001 ; Cin = 1'b0 ;
#5; 
A = 4'b1011 ; B = 4'b1010 ; Cin = 1'b0 ;
#5; 
A = 4'b1011 ; B = 4'b1011 ; Cin = 1'b0 ;
#5; 
A = 4'b1011 ; B = 4'b1100 ; Cin = 1'b0 ;
#5; 
A = 4'b1011 ; B = 4'b1101 ; Cin = 1'b0 ;
#5; 
A = 4'b1011 ; B = 4'b1110 ; Cin = 1'b0 ;
#5; 
A = 4'b1011 ; B = 4'b1111 ; Cin = 1'b0 ;
#5; 
A = 4'b1100 ; B = 4'b0000 ; Cin = 1'b0 ;
#5; 
A = 4'b1100 ; B = 4'b0001 ; Cin = 1'b0 ;
#5; 
A = 4'b1100 ; B = 4'b0010 ; Cin = 1'b0 ;
#5; 
A = 4'b1100 ; B = 4'b0011 ; Cin = 1'b0 ;
#5; 
A = 4'b1100 ; B = 4'b0100 ; Cin = 1'b0 ;
#5; 
A = 4'b1100 ; B = 4'b0101 ; Cin = 1'b0 ;
#5; 
A = 4'b1100 ; B = 4'b0110 ; Cin = 1'b0 ;
#5; 
A = 4'b1100 ; B = 4'b0111 ; Cin = 1'b0 ;
#5; 
A = 4'b1100 ; B = 4'b1000 ; Cin = 1'b0 ;
#5; 
A = 4'b1100 ; B = 4'b1001 ; Cin = 1'b0 ;
#5; 
A = 4'b1100 ; B = 4'b1010 ; Cin = 1'b0 ;
#5; 
A = 4'b1100 ; B = 4'b1011 ; Cin = 1'b0 ;
#5; 
A = 4'b1100 ; B = 4'b1100 ; Cin = 1'b0 ;
#5; 
A = 4'b1100 ; B = 4'b1101 ; Cin = 1'b0 ;
#5; 
A = 4'b1100 ; B = 4'b1110 ; Cin = 1'b0 ;
#5; 
A = 4'b1100 ; B = 4'b1111 ; Cin = 1'b0 ;
#5; 
A = 4'b1101 ; B = 4'b0000 ; Cin = 1'b0 ;
#5; 
A = 4'b1101 ; B = 4'b0001 ; Cin = 1'b0 ;
#5; 
A = 4'b1101 ; B = 4'b0010 ; Cin = 1'b0 ;
#5; 
A = 4'b1101 ; B = 4'b0011 ; Cin = 1'b0 ;
#5; 
A = 4'b1101 ; B = 4'b0100 ; Cin = 1'b0 ;
#5; 
A = 4'b1101 ; B = 4'b0101 ; Cin = 1'b0 ;
#5; 
A = 4'b1101 ; B = 4'b0110 ; Cin = 1'b0 ;
#5; 
A = 4'b1101 ; B = 4'b0111 ; Cin = 1'b0 ;
#5; 
A = 4'b1101 ; B = 4'b1000 ; Cin = 1'b0 ;
#5; 
A = 4'b1101 ; B = 4'b1001 ; Cin = 1'b0 ;
#5; 
A = 4'b1101 ; B = 4'b1010 ; Cin = 1'b0 ;
#5; 
A = 4'b1101 ; B = 4'b1011 ; Cin = 1'b0 ;
#5; 
A = 4'b1101 ; B = 4'b1100 ; Cin = 1'b0 ;
#5; 
A = 4'b1101 ; B = 4'b1101 ; Cin = 1'b0 ;
#5; 
A = 4'b1101 ; B = 4'b1110 ; Cin = 1'b0 ;
#5; 
A = 4'b1101 ; B = 4'b1111 ; Cin = 1'b0 ;
#5; 
A = 4'b1110 ; B = 4'b0000 ; Cin = 1'b0 ;
#5; 
A = 4'b1110 ; B = 4'b0001 ; Cin = 1'b0 ;
#5; 
A = 4'b1110 ; B = 4'b0010 ; Cin = 1'b0 ;
#5; 
A = 4'b1110 ; B = 4'b0011 ; Cin = 1'b0 ;
#5; 
A = 4'b1110 ; B = 4'b0100 ; Cin = 1'b0 ;
#5; 
A = 4'b1110 ; B = 4'b0101 ; Cin = 1'b0 ;
#5; 
A = 4'b1110 ; B = 4'b0110 ; Cin = 1'b0 ;
#5; 
A = 4'b1110 ; B = 4'b0111 ; Cin = 1'b0 ;
#5; 
A = 4'b1110 ; B = 4'b1000 ; Cin = 1'b0 ;
#5; 
A = 4'b1110 ; B = 4'b1001 ; Cin = 1'b0 ;
#5; 
A = 4'b1110 ; B = 4'b1010 ; Cin = 1'b0 ;
#5; 
A = 4'b1110 ; B = 4'b1011 ; Cin = 1'b0 ;
#5; 
A = 4'b1110 ; B = 4'b1100 ; Cin = 1'b0 ;
#5; 
A = 4'b1110 ; B = 4'b1101 ; Cin = 1'b0 ;
#5; 
A = 4'b1110 ; B = 4'b1110 ; Cin = 1'b0 ;
#5; 
A = 4'b1110 ; B = 4'b1111 ; Cin = 1'b0 ;
#5; 
A = 4'b1111 ; B = 4'b0000 ; Cin = 1'b0 ;
#5; 
A = 4'b1111 ; B = 4'b0001 ; Cin = 1'b0 ;
#5; 
A = 4'b1111 ; B = 4'b0010 ; Cin = 1'b0 ;
#5; 
A = 4'b1111 ; B = 4'b0011 ; Cin = 1'b0 ;
#5; 
A = 4'b1111 ; B = 4'b0100 ; Cin = 1'b0 ;
#5; 
A = 4'b1111 ; B = 4'b0101 ; Cin = 1'b0 ;
#5; 
A = 4'b1111 ; B = 4'b0110 ; Cin = 1'b0 ;
#5; 
A = 4'b1111 ; B = 4'b0111 ; Cin = 1'b0 ;
#5; 
A = 4'b1111 ; B = 4'b1000 ; Cin = 1'b0 ;
#5; 
A = 4'b1111 ; B = 4'b1001 ; Cin = 1'b0 ;
#5; 
A = 4'b1111 ; B = 4'b1010 ; Cin = 1'b0 ;
#5; 
A = 4'b1111 ; B = 4'b1011 ; Cin = 1'b0 ;
#5; 
A = 4'b1111 ; B = 4'b1100 ; Cin = 1'b0 ;
#5; 
A = 4'b1111 ; B = 4'b1101 ; Cin = 1'b0 ;
#5; 
A = 4'b1111 ; B = 4'b1110 ; Cin = 1'b0 ;
#5; 
A = 4'b1111 ; B = 4'b1111 ; Cin = 1'b0 ;
#5;
A = 4'b1111 ; B = 4'b1111 ; Cin = 1'b0 ;

end
endmodule

4-Bit_Adder/4bitadder.vcd
$date
	Mon Mar 19 18:52:29 2018
$end
$version
	Icarus Verilog
$end
$timescale
	1s
$end
$scope module testbench $end
$var wire 1 ! Cout $end
$var wire 4 " Sum [3:0] $end
$var reg 4 # A [3:0] $end
$var reg 4 $ B [3:0] $end
$var reg 1 % Cin $end
$scope module tb $end
$var wire 4 & A [3:0] $end
$var wire 4 ' B [3:0] $end
$var wire 1 ( Cin $end
$var wire 1 ! Cout $end
$var wire 4 ) Sum [3:0] $end
$var wire 1 * c1 $end
$var wire 1 + c2 $end
$var wire 1 , c3 $end
$scope module f1 $end
$var wire 1 - a $end
$var wire 1 . b $end
$var wire 1 ( cin $end
$var wire 1 * cout $end
$var wire 1 / sum $end
$upscope $end
$scope module f2 $end
$var wire 1 0 a $end
$var wire 1 1 b $end
$var wire 1 * cin $end
$var wire 1 + cout $end
$var wire 1 2 sum $end
$upscope $end
$scope module f3 $end
$var wire 1 3 a $end
$var wire 1 4 b $end
$var wire 1 + cin $end
$var wire 1 , cout $end
$var wire 1 5 sum $end
$upscope $end
$scope module f4 $end
$var wire 1 6 a $end
$var wire 1 7 b $end
$var wire 1 , cin $end
$var wire 1 ! cout $end
$var wire 1 8 sum $end
$upscope $end
$upscope $end
$upscope $end
$enddefinitions $end
#0
$dumpvars
08
07
06
05
04
03
02
01
00
0/
0.
0-
0,
0+
0*
b0 )
0(
b0 '
b0 &
0%
b0 $
b0 #
b0 "
0!
$end
#5
1/
b1 "
b1 )
1.
b1 $
b1 '
#10
0/
12
b10 "
b10 )
0.
11
b10 $
b10 '
#15
1/
b11 "
b11 )
1.
b11 $
b11 '
#20
0/
02
15
b100 "
b100 )
0.
01
14
b100 $
b100 '
#25
1/
b101 "
b101 )
1.
b101 $
b101 '
#30
0/
12
b110 "
b110 )
0.
11
b110 $
b110 '
#35
1/
b111 "
b111 )
1.
b111 $
b111 '
#40
0/
02
05
18
b1000 "
b1000 )
0.
01
04
17
b1000 $
b1000 '
#45
1/
b1001 "
b1001 )
1.
b1001 $
b1001 '
#50
0/
12
b1010 "
b1010 )
0.
11
b1010 $
b1010 '
#55
1/
b1011 "
b1011 )
1.
b1011 $
b1011 '
#60
0/
02
15
b1100 "
b1100 )
0.
01
14
b1100 $
b1100 '
#65
1/
b1101 "
b1101 )
1.
b1101 $
b1101 '
#70
0/
12
b1110 "
b1110 )
0.
11
b1110 $
b1110 '
#75
1/
b1111 "
b1111 )
1.
b1111 $
b1111 '
#80
02
05
08
b1 "
b1 )
0.
01
04
07
1-
b0 $
b0 '
b1 #
b1 &
#85
12
0/
b10 "
b10 )
1*
1.
b1 $
b1 '
#90
05
0+
1/
0*
12
b11 "
b11 )
0.
11
b10 $
b10 '
#95
15
1+
02
0/
b100 "
b100 )
1*
1.
b11 $
b11 '
#100
08
0+
0,
1/
0*
02
15
b101 "
b101 )
0.
01
14
b100 $
b100 '
#105
12
0/
b110 "
b110 )
1*
1.
b101 $
b101 '
#110
08
0,
15
0+
1/
0*
12
b111 "
b111 )
0.
11
b110 $
b110 '
#115
18
1,
05
1+
02
0/
b1000 "
b1000 )
1*
1.
b111 $
b111 '
#120
0+
0,
0!
1/
0*
02
05
18
b1001 "
b1001 )
0.
01
04
17
b1000 $
b1000 '
#125
12
0/
b1010 "
b1010 )
1*
1.
b1001 $
b1001 '
#130
05
0+
1/
0*
12
b1011 "
b1011 )
0.
11
b1010 $
b1010 '
#135
15
1+
02
0/
b1100 "
b1100 )
1*
1.
b1011 $
b1011 '
#140
0!
18
0+
0,
1/
0*
02
15
b1101 "
b1101 )
0.
01
14
b1100 $
b1100 '
#145
12
0/
b1110 "
b1110 )
1*
1.
b1101 $
b1101 '
#150
0!
18
0,
15
0+
1/
0*
12
b1111 "
b1111 )
0.
11
b1110 $
b1110 '
#155
1!
08
1,
05
1+
02
0/
b0 "
b0 )
1*
1.
b1111 $
b1111 '
#160
0+
0,
0!
12
05
08
b10 "
b10 )
0*
0.
01
04
07
0-
10
b0 $
b0 '
b10 #
b10 &
#165
1/
b11 "
b11 )
1.
b1 $
b1 '
#170
15
0/
02
b100 "
b100 )
1+
0.
11
b10 $
b10 '
#175
1/
b101 "
b101 )
1.
b11 $
b11 '
#180
08
0,
0/
12
0+
15
b110 "
b110 )
0.
01
14
b100 $
b100 '
#185
1/
b111 "
b111 )
1.
b101 $
b101 '
#190
18
1,
05
0/
02
b1000 "
b1000 )
1+
0.
11
b110 $
b110 '
#195
1/
b1001 "
b1001 )
1.
b111 $
b111 '
#200
0,
0!
0/
12
0+
05
18
b1010 "
b1010 )
0.
01
04
17
b1000 $
b1000 '
#205
1/
b1011 "
b1011 )
1.
b1001 $
b1001 '
#210
15
0/
02
b1100 "
b1100 )
1+
0.
11
b1010 $
b1010 '
#215
1/
b1101 "
b1101 )
1.
b1011 $
b1011 '
#220
0!
18
0,
0/
12
0+
15
b1110 "
b1110 )
0.
01
14
b1100 $
b1100 '
#225
1/
b1111 "
b1111 )
1.
b1101 $
b1101 '
#230
1!
08
1,
05
0/
02
b0 "
b0 )
1+
0.
11
b1110 $
b1110 '
#235
1/
b1 "
b1 )
1.
b1111 $
b1111 '
#240
0,
0!
12
0+
05
08
b11 "
b11 )
0.
01
04
07
1-
b0 $
b0 '
b11 #
b11 &
#245
15
1+
02
0/
b100 "
b100 )
1*
1.
b1 $
b1 '
#250
1/
0*
02
b101 "
b101 )
0.
11
b10 $
b10 '
#255
12
0/
b110 "
b110 )
1*
1.
b11 $
b11 '
#260
0+
08
0,
1/
0*
12
15
b111 "
b111 )
0.
01
14
b100 $
b100 '
#265
18
1,
05
1+
02
0/
b1000 "
b1000 )
1*
1.
b101 $
b101 '
#270
1/
0*
02
b1001 "
b1001 )
0.
11
b110 $
b110 '
#275
12
0/
b1010 "
b1010 )
1*
1.
b111 $
b111 '
#280
0+
0,
0!
1/
0*
12
05
18
b1011 "
b1011 )
0.
01
04
17
b1000 $
b1000 '
#285
15
1+
02
0/
b1100 "
b1100 )
1*
1.
b1001 $
b1001 '
#290
1/
0*
02
b1101 "
b1101 )
0.
11
b1010 $
b1010 '
#295
12
0/
b1110 "
b1110 )
1*
1.
b1011 $
b1011 '
#300
0!
0+
18
0,
1/
0*
12
15
b1111 "
b1111 )
0.
01
14
b1100 $
b1100 '
#305
1!
08
1,
05
1+
02
0/
b0 "
b0 )
1*
1.
b1101 $
b1101 '
#310
1/
0*
02
b1 "
b1 )
0.
11
b1110 $
b1110 '
#315
12
0/
b10 "
b10 )
1*
1.
b1111 $
b1111 '
#320
0,
0!
02
15
08
b100 "
b100 )
0*
0+
0.
01
04
07
0-
00
13
b0 $
b0 '
b100 #
b100 &
#325
1/
b101 "
b101 )
1.
b1 $
b1 '
#330
0/
12
b110 "
b110 )
0.
11
b10 $
b10 '
#335
1/
b111 "
b111 )
1.
b11 $
b11 '
#340
18
0/
02
05
b1000 "
b1000 )
1,
0.
01
14
b100 $
b100 '
#345
1/
b1001 "
b1001 )
1.
b101 $
b101 '
#350
0/
12
b1010 "
b1010 )
0.
11
b110 $
b110 '
#355
1/
b1011 "
b1011 )
1.
b111 $
b111 '
#360
0!
0/
02
15
0,
18
b1100 "
b1100 )
0.
01
04
17
b1000 $
b1000 '
#365
1/
b1101 "
b1101 )
1.
b1001 $
b1001 '
#370
0/
12
b1110 "
b1110 )
0.
11
b1010 $
b1010 '
#375
1/
b1111 "
b1111 )
1.
b1011 $
b1011 '
#380
1!
08
0/
02
05
b0 "
b0 )
1,
0.
01
14
b1100 $
b1100 '
#385
1/
b1 "
b1 )
1.
b1101 $
b1101 '
#390
0/
12
b10 "
b10 )
0.
11
b1110 $
b1110 '
#395
1/
b11 "
b11 )
1.
b1111 $
b1111 '
#400
0!
02
15
0,
08
b101 "
b101 )
0.
01
04
07
1-
b0 $
b0 '
b101 #
b101 &
#405
12
0/
b110 "
b110 )
1*
1.
b1 $
b1 '
#410
08
0,
15
0+
1/
0*
12
b111 "
b111 )
0.
11
b10 $
b10 '
#415
18
1,
05
1+
02
0/
b1000 "
b1000 )
1*
1.
b11 $
b11 '
#420
0+
1/
0*
02
05
b1001 "
b1001 )
0.
01
14
b100 $
b100 '
#425
12
0/
b1010 "
b1010 )
1*
1.
b101 $
b101 '
