BCD_Adder/bcd.v
module bcd_adder(a,b,carry_in,sum,carry);

	input [3:0] a,b;
	input carry_in;

	output [3:0] sum;
	output carry;


	reg [4:0] sum_temp;
	reg [3:0] sum;
	reg carry;


	always @(a,b,carry_in)
	begin
		sum_temp = a+b+carry_in; 
		if(sum_temp > 9)
		begin
			sum_temp = sum_temp+6; //add 6, if result is more than 9.
			carry = 1; //set the carry output
			sum = sum_temp[3:0];
		end
		else
		begin
			carry = 0;
			sum = sum_temp[3:0];
		end
	end
endmodule

module tb_bcdadder;
	
	reg [3:0] a;
	reg [3:0] b;
	reg carry_in;

	
	wire [3:0] sum;
	wire carry;
	
	
	bcd_adder uut (.a(a),.b(b),.carry_in(carry_in),.sum(sum),.carry(carry));
	initial begin
	$monitor("A = %b ,B= %b , Sum = %b , carry = %b ",a,b,sum,carry);
	$dumpfile("bcd.vcd");
	$dumpvars;	
	
a = 0; b = 0; carry_in = 0;#5
a = 0; b = 1; carry_in = 0;#5
a = 0; b = 2; carry_in = 0;#5
a = 0; b = 3; carry_in = 0;#5
a = 0; b = 4; carry_in = 0;#5
a = 0; b = 5; carry_in = 0;#5
a = 0; b = 6; carry_in = 0;#5
a = 0; b = 7; carry_in = 0;#5
a = 0; b = 8; carry_in = 0;#5
a = 0; b = 9; carry_in = 0;#5

a = 1; b = 0; carry_in = 0;#5
a = 1; b = 1; carry_in = 0;#5
a = 1; b = 2; carry_in = 0;#5
a = 1; b = 3; carry_in = 0;#5
a = 1; b = 4; carry_in = 0;#5
a = 1; b = 5; carry_in = 0;#5
a = 1; b = 6; carry_in = 0;#5
a = 1; b = 7; carry_in = 0;#5
a = 1; b = 8; carry_in = 0;#5
a = 1; b = 9; carry_in = 0;#5

a = 2; b = 0; carry_in = 0;#5
a = 2; b = 1; carry_in = 0;#5
a = 2; b = 2; carry_in = 0;#5
a = 2; b = 3; carry_in = 0;#5
a = 2; b = 4; carry_in = 0;#5
a = 2; b = 5; carry_in = 0;#5
a = 2; b = 6; carry_in = 0;#5
a = 2; b = 7; carry_in = 0;#5
a = 2; b = 8; carry_in = 0;#5
a = 2; b = 9; carry_in = 0;#5

a = 3; b = 0; carry_in = 0;#5
a = 3; b = 1; carry_in = 0;#5
a = 3; b = 2; carry_in = 0;#5
a = 3; b = 3; carry_in = 0;#5
a = 3; b = 4; carry_in = 0;#5
a = 3; b = 5; carry_in = 0;#5
a = 3; b = 6; carry_in = 0;#5
a = 3; b = 7; carry_in = 0;#5
a = 3; b = 8; carry_in = 0;#5
a = 3; b = 9; carry_in = 0;#5

a = 4; b = 0; carry_in = 0;#5
a = 4; b = 1; carry_in = 0;#5
a = 4; b = 2; carry_in = 0;#5
a = 4; b = 3; carry_in = 0;#5
a = 4; b = 4; carry_in = 0;#5
a = 4; b = 5; carry_in = 0;#5
a = 4; b = 6; carry_in = 0;#5
a = 4; b = 7; carry_in = 0;#5
a = 4; b = 8; carry_in = 0;#5
a = 4; b = 9; carry_in = 0;#5

a = 5; b = 0; carry_in = 0;#5
a = 5; b = 1; carry_in = 0;#5
a = 5; b = 2; carry_in = 0;#5
a = 5; b = 3; carry_in = 0;#5
a = 5; b = 4; carry_in = 0;#5
a = 5; b = 5; carry_in = 0;#5
a = 5; b = 6; carry_in = 0;#5
a = 5; b = 7; carry_in = 0;#5
a = 5; b = 8; carry_in = 0;#5
a = 5; b = 9; carry_in = 0;#5

a = 6; b = 0; carry_in = 0;#5
a = 6; b = 1; carry_in = 0;#5
a = 6; b = 2; carry_in = 0;#5
a = 6; b = 3; carry_in = 0;#5
a = 6; b = 4; carry_in = 0;#5
a = 6; b = 5; carry_in = 0;#5
a = 6; b = 6; carry_in = 0;#5
a = 6; b = 7; carry_in = 0;#5
a = 6; b = 8; carry_in = 0;#5
a = 6; b = 9; carry_in = 0;#5

a = 7; b = 0; carry_in = 0;#5
a = 7; b = 1; carry_in = 0;#5
a = 7; b = 2; carry_in = 0;#5
a = 7; b = 3; carry_in = 0;#5
a = 7; b = 4; carry_in = 0;#5
a = 7; b = 5; carry_in = 0;#5
a = 7; b = 6; carry_in = 0;#5
a = 7; b = 7; carry_in = 0;#5
a = 7; b = 8; carry_in = 0;#5
a = 7; b = 9; carry_in = 0;#5

a = 8; b = 0; carry_in = 0;#5
a = 8; b = 1; carry_in = 0;#5
a = 8; b = 2; carry_in = 0;#5
a = 8; b = 3; carry_in = 0;#5
a = 8; b = 4; carry_in = 0;#5
a = 8; b = 5; carry_in = 0;#5
a = 8; b = 6; carry_in = 0;#5
a = 8; b = 7; carry_in = 0;#5
a = 8; b = 8; carry_in = 0;#5
a = 8; b = 9; carry_in = 0;#5

a = 9; b = 0; carry_in = 0;#5
a = 9; b = 1; carry_in = 0;#5
a = 9; b = 2; carry_in = 0;#5
a = 9; b = 3; carry_in = 0;#5
a = 9; b = 4; carry_in = 0;#5
a = 9; b = 5; carry_in = 0;#5
a = 9; b = 6; carry_in = 0;#5
a = 9; b = 7; carry_in = 0;#5
a = 9; b = 8; carry_in = 0;#5
a = 9; b = 9; carry_in = 0;
	end
endmodule

BCD_Adder/bcd.vcd
$date
	Mon Mar 19 18:56:17 2018
$end
$version
	Icarus Verilog
$end
$timescale
	1s
$end
$scope module tb_bcdadder $end
$var wire 1 ! carry $end
$var wire 4 " sum [3:0] $end
$var reg 4 # a [3:0] $end
$var reg 4 $ b [3:0] $end
$var reg 1 % carry_in $end
$scope module uut $end
$var wire 4 & a [3:0] $end
$var wire 4 ' b [3:0] $end
$var wire 1 ( carry_in $end
$var reg 1 ) carry $end
$var reg 4 * sum [3:0] $end
$var reg 5 + sum_temp [4:0] $end
$upscope $end
$upscope $end
$enddefinitions $end
#0
$dumpvars
b0 +
b0 *
0)
0(
b0 '
b0 &
0%
b0 $
b0 #
b0 "
0!
$end
#5
b1 *
b1 "
b1 +
b1 $
b1 '
#10
b10 *
b10 "
b10 +
b10 $
b10 '
#15
b11 *
b11 "
b11 +
b11 $
b11 '
#20
b100 *
b100 "
b100 +
b100 $
b100 '
#25
b101 *
b101 "
b101 +
b101 $
b101 '
#30
b110 *
b110 "
b110 +
b110 $
b110 '
#35
b111 *
b111 "
b111 +
b111 $
b111 '
#40
b1000 *
b1000 "
b1000 +
b1000 $
b1000 '
#45
b1001 *
b1001 "
b1001 +
b1001 $
b1001 '
#50
b1 *
b1 "
b1 +
b0 $
b0 '
b1 #
b1 &
#55
b10 *
b10 "
b10 +
b1 $
b1 '
#60
b11 *
b11 "
b11 +
b10 $
b10 '
#65
b100 *
b100 "
b100 +
b11 $
b11 '
#70
b101 *
b101 "
b101 +
b100 $
b100 '
#75
b110 *
b110 "
b110 +
b101 $
b101 '
#80
b111 *
b111 "
b111 +
b110 $
b110 '
#85
b1000 *
b1000 "
b1000 +
b111 $
b111 '
#90
b1001 *
b1001 "
b1001 +
b1000 $
b1000 '
#95
b0 *
b0 "
1)
1!
b10000 +
b1001 $
b1001 '
#100
b10 *
b10 "
0)
0!
b10 +
b0 $
b0 '
b10 #
b10 &
#105
b11 *
b11 "
b11 +
b1 $
b1 '
#110
b100 *
b100 "
b100 +
b10 $
b10 '
#115
b101 *
b101 "
b101 +
b11 $
b11 '
#120
b110 *
b110 "
b110 +
b100 $
b100 '
#125
b111 *
b111 "
b111 +
b101 $
b101 '
#130
b1000 *
b1000 "
b1000 +
b110 $
b110 '
#135
b1001 *
b1001 "
b1001 +
b111 $
b111 '
#140
b0 *
b0 "
1)
1!
b10000 +
b1000 $
b1000 '
#145
b1 *
b1 "
b10001 +
b1001 $
b1001 '
#150
b11 *
b11 "
0)
0!
b11 +
b0 $
b0 '
b11 #
b11 &
#155
b100 *
b100 "
b100 +
b1 $
b1 '
#160
b101 *
b101 "
b101 +
b10 $
b10 '
#165
b110 *
b110 "
b110 +
b11 $
b11 '
#170
b111 *
b111 "
b111 +
b100 $
b100 '
#175
b1000 *
b1000 "
b1000 +
b101 $
b101 '
#180
b1001 *
b1001 "
b1001 +
b110 $
b110 '
#185
b0 *
b0 "
1)
1!
b10000 +
b111 $
b111 '
#190
b1 *
b1 "
b10001 +
b1000 $
b1000 '
#195
b10 *
b10 "
b10010 +
b1001 $
b1001 '
#200
b100 *
b100 "
0)
0!
b100 +
b0 $
b0 '
b100 #
b100 &
#205
b101 *
b101 "
b101 +
b1 $
b1 '
#210
b110 *
b110 "
b110 +
b10 $
b10 '
#215
b111 *
b111 "
b111 +
b11 $
b11 '
#220
b1000 *
b1000 "
b1000 +
b100 $
b100 '
#225
b1001 *
b1001 "
b1001 +
b101 $
b101 '
#230
b0 *
b0 "
1)
1!
b10000 +
b110 $
b110 '
#235
b1 *
b1 "
b10001 +
b111 $
b111 '
#240
b10 *
b10 "
b10010 +
b1000 $
b1000 '
#245
b11 *
b11 "
b10011 +
b1001 $
b1001 '
#250
b101 *
b101 "
0)
0!
b101 +
b0 $
b0 '
b101 #
b101 &
#255
b110 *
b110 "
b110 +
b1 $
b1 '
#260
b111 *
b111 "
b111 +
b10 $
b10 '
#265
b1000 *
b1000 "
b1000 +
b11 $
b11 '
#270
b1001 *
b1001 "
b1001 +
b100 $
b100 '
#275
b0 *
b0 "
1)
1!
b10000 +
b101 $
b101 '
#280
b1 *
b1 "
b10001 +
b110 $
b110 '
#285
b10 *
b10 "
b10010 +
b111 $
b111 '
#290
b11 *
b11 "
b10011 +
b1000 $
b1000 '
#295
b100 *
b100 "
b10100 +
b1001 $
b1001 '
#300
b110 *
b110 "
0)
0!
b110 +
b0 $
b0 '
b110 #
b110 &
#305
b111 *
b111 "
b111 +
b1 $
b1 '
#310
b1000 *
b1000 "
b1000 +
b10 $
b10 '
#315
b1001 *
b1001 "
b1001 +
b11 $
b11 '
#320
b0 *
b0 "
1)
1!
b10000 +
b100 $
b100 '
#325
b1 *
b1 "
b10001 +
b101 $
b101 '
#330
b10 *
b10 "
b10010 +
b110 $
b110 '
#335
b11 *
b11 "
b10011 +
b111 $
b111 '
#340
b100 *
b100 "
b10100 +
b1000 $
b1000 '
#345
b101 *
b101 "
b10101 +
b1001 $
b1001 '
#350
b111 *
b111 "
0)
0!
b111 +
b0 $
b0 '
b111 #
b111 &
#355
b1000 *
b1000 "
b1000 +
b1 $
b1 '
#360
b1001 *
b1001 "
b1001 +
b10 $
b10 '
#365
b0 *
b0 "
1)
1!
b10000 +
b11 $
b11 '
#370
b1 *
b1 "
b10001 +
b100 $
b100 '
#375
b10 *
b10 "
b10010 +
b101 $
b101 '
#380
b11 *
b11 "
b10011 +
b110 $
b110 '
#385
b100 *
b100 "
b10100 +
b111 $
b111 '
#390
b101 *
b101 "
b10101 +
b1000 $
b1000 '
#395
b110 *
b110 "
b10110 +
b1001 $
b1001 '
#400
b1000 *
b1000 "
0)
0!
b1000 +
b0 $
b0 '
b1000 #
b1000 &
#405
b1001 *
b1001 "
b1001 +
b1 $
b1 '
#410
b0 *
b0 "
1)
1!
b10000 +
b10 $
b10 '
#415
b1 *
b1 "
b10001 +
b11 $
b11 '
#420
b10 *
b10 "
b10010 +
b100 $
b100 '
#425
b11 *
b11 "
b10011 +
b101 $
b101 '
#430
b100 *
b100 "
b10100 +
b110 $
b110 '
#435
b101 *
b101 "
b10101 +
b111 $
b111 '
#440
b110 *
b110 "
b10110 +
b1000 $
b1000 '
#445
b111 *
b111 "
b10111 +
b1001 $
b1001 '
#450
b1001 *
b1001 "
0)
0!
b1001 +
b0 $
b0 '
b1001 #
b1001 &
#455
b0 *
b0 "
1)
1!
b10000 +
b1 $
b1 '
#460
b1 *
b1 "
b10001 +
b10 $
b10 '
#465
b10 *
b10 "
b10010 +
b11 $
b11 '
#470
b11 *
b11 "
b10011 +
b100 $
b100 '
#475
b100 *
b100 "
b10100 +
b101 $
b101 '
#480
b101 *
b101 "
b10101 +
b110 $
b110 '
#485
b110 *
b110 "
b10110 +
b111 $
b111 '
#490
b111 *
b111 "
b10111 +
b1000 $
b1000 '
#495
b1000 *
b1000 "
b11000 +
b1001 $
b1001 '
