Comparator/comparator.v
module comparator(A,B,less,	equal,greater);
	
	input [1:0] A;
	input [1:0] B;

	output less;
	output equal;
	output greater;

	reg less;
	reg equal;
	reg greater;

	always @(A or B)
	begin
		if(A > B)
		begin //check if A is bigger than B.
			less = 0;
			equal = 0;
			greater = 1;
		end
		else if(A == B) 
		begin //Check if A is equal to B
			less = 0;
			equal = 1;
			greater = 0;
		end
		else
		begin //Otherwise - check for A less than B.
			less = 1;
			equal = 0;
			greater =0;
		end
	end
endmodule
module tb_tm;

	reg [1:0] A;
	reg [1:0] B;

	wire less;
	wire equal;
	wire greater;

	comparator uut (.A(A),.B(B),.less(less),.equal(equal),.greater(greater));
	initial begin
		$monitor("A = %b ,B= %b , L = %b , E = %b , G = %b",A,B,less,equal,greater);
		$dumpfile("comparator.vcd");
		$dumpvars;

		A = 2'b00;B = 2'b00;
		#5;
		A = 2'b00;B = 2'b01;
		#5;
		A = 2'b00;B = 2'b10;
		#5;
		A = 2'b00;B = 2'b11;
		#5;
		A = 2'b01;B = 2'b00;
		#5;
		A = 2'b01;B = 2'b01;
		#5;
		A = 2'b01;B = 2'b10;
		#5;
		A = 2'b01;B = 2'b11;
		#5;
		A = 2'b10;B = 2'b00;
		#5;
		A = 2'b10;B = 2'b01;
		#5;
		A = 2'b10;B = 2'b10;
		#5;
		A = 2'b10;B = 2'b11;
		#5;
		A = 2'b11;B = 2'b00;
		#5;
		A = 2'b11;B = 2'b01;
		#5;
		A = 2'b11;B = 2'b10;
		#5;
		A = 2'b11;B = 2'b11;
		#5;
		A = 2'b11;B = 2'b11;
	end
endmodule

Comparator/comparator.vcd
$date
	Mon Mar 19 18:38:49 2018
$end
$version
	Icarus Verilog
$end
$timescale
	1s
$end
$scope module tb_tm $end
$var wire 1 ! equal $end
$var wire 1 " greater $end
$var wire 1 # less $end
$var reg 2 $ A [1:0] $end
$var reg 2 % B [1:0] $end
$scope module uut $end
$var wire 2 & A [1:0] $end
$var wire 2 ' B [1:0] $end
$var reg 1 ( equal $end
$var reg 1 ) greater $end
$var reg 1 * less $end
$upscope $end
$upscope $end
$enddefinitions $end
#0
$dumpvars
0*
0)
1(
b0 '
b0 &
b0 %
b0 $
0#
0"
1!
$end
#5
0(
0!
1*
1#
b1 %
b1 '
#10
b10 %
b10 '
#15
b11 %
b11 '
#20
1)
1"
0*
0#
b0 %
b0 '
b1 $
b1 &
#25
0)
0"
1(
1!
b1 %
b1 '
#30
0(
0!
1*
1#
b10 %
b10 '
#35
b11 %
b11 '
#40
1)
1"
0*
0#
b0 %
b0 '
b10 $
b10 &
#45
b1 %
b1 '
#50
0)
0"
1(
1!
b10 %
b10 '
#55
0(
0!
1*
1#
b11 %
b11 '
#60
1)
1"
0*
0#
b0 %
b0 '
b11 $
b11 &
#65
b1 %
b1 '
#70
b10 %
b10 '
#75
0)
0"
1(
1!
b11 %
b11 '
