Flip-Flops/JK_Master_Slave/jkmaster.v
module jkmaster(j,k,cp,qb,q,t);

input j;
input k;
input cp;
input qb;
output q;
output t;

wire q1,q2,q3,q4,q5,q6;


and a1(q1,j,cp,qb);
and a2(q2,k,cp,~qb);
xor x1(q3,q1,~qb);
xor x2(q4,q2,q3);
and a3(q5,q3,qb,~cp);
and a4(q6,q4,~qb,~cp);
xor x3(q,q5,~qb);
xor x4(t,q6,q);

endmodule

module testbench();

reg j,k,cp,qb;
wire q,t;

jkmaster f1(j,k,cp,qb,q,t);

initial
begin

$monitor("CP = %b : Q[1] = %b : J = %b : K = %b : Q = %b : Q` = %b",cp,qb,j,k,q,t);
$dumpfile("jkmaster.vcd");
$dumpvars;

cp = 1'b1 ; qb = 1'b0;
j = 1'b0 ; k = 1'b0 ; #5 
j = 1'b0 ; k = 1'b1 ; #5 
j = 1'b1 ; k = 1'b0 ; #5 
j = 1'b1 ; k = 1'b1 ; #5 
j = 1'b1 ; k = 1'b1 ; #5
cp = 1'b1 ; qb = 1'b1;
j = 1'b0 ; k = 1'b0 ; #5 
j = 1'b0 ; k = 1'b1 ; #5 
j = 1'b1 ; k = 1'b0 ; #5 
j = 1'b1 ; k = 1'b1 ; #5 
j = 1'b1 ; k = 1'b1 ; #5
cp = 1'b0 ; qb = 1'b0;
j = 1'b0 ; k = 1'b0 ; #5 
j = 1'b0 ; k = 1'b1 ; #5 
j = 1'b1 ; k = 1'b0 ; #5 
j = 1'b1 ; k = 1'b1 ; #5 
j = 1'b1 ; k = 1'b1 ; #5
cp = 1'b0 ; qb = 1'b1;
j = 1'b0 ; k = 1'b0 ; #5 
j = 1'b0 ; k = 1'b1 ; #5 
j = 1'b1 ; k = 1'b0 ; #5 
j = 1'b1 ; k = 1'b1 ; #5 
j = 1'b1 ; k = 1'b1 ; #5
j = 1'b1 ; k = 1'b1 ;

end

endmodule

Flip-Flops/JK_Master_Slave/jkmaster.vcd
$date
	Mon Mar 19 19:07:44 2018
$end
$version
	Icarus Verilog
$end
$timescale
	1s
$end
$scope module testbench $end
$var wire 1 ! q $end
$var wire 1 " t $end
$var reg 1 # cp $end
$var reg 1 $ j $end
$var reg 1 % k $end
$var reg 1 & qb $end
$scope module f1 $end
$var wire 1 ' cp $end
$var wire 1 ( j $end
$var wire 1 ) k $end
$var wire 1 ! q $end
$var wire 1 * q1 $end
$var wire 1 + q2 $end
$var wire 1 , q3 $end
$var wire 1 - q4 $end
$var wire 1 . q5 $end
$var wire 1 / q6 $end
$var wire 1 0 qb $end
$var wire 1 " t $end
$upscope $end
$upscope $end
$enddefinitions $end
#0
$dumpvars
00
0/
0.
1-
1,
0+
0*
0)
0(
1'
0&
0%
0$
1#
1"
1!
$end
#5
0-
1+
1%
1)
#10
1-
0+
0%
0)
1$
1(
#15
0-
1+
1%
1)
#25
0"
0,
0!
0+
0%
0)
0$
0(
1&
10
#30
1%
1)
#35
1-
1,
1*
0%
0)
1$
1(
#40
1%
1)
#50
1!
1/
0*
0%
0)
0$
0(
0&
00
0#
0'
#55
1%
1)
#60
0%
0)
1$
1(
#65
1%
1)
#75
0!
0-
0"
0,
0/
0.
0%
0)
0$
0(
1&
10
#80
1%
1)
#85
0%
0)
1$
1(
#90
1%
1)
