Full_Adder/fulladder.v
module full_adder(a,b,cin,sum,cout);
input [2:0]a;
input [2:0]b;
input [2:0]cin;
output [2:0]sum;
output [2:0]cout;

assign sum = a^b^cin;
assign cout = (a & b) | (cin & (a^b)); 

endmodule


module tb_full_adder;

     reg [2:0]a;
	 reg [2:0]b;
	 reg [2:0]cin;
     wire [2:0]sum;
	 wire [2:0]cout;
	 integer i,j;
	 
     full_adder Fa (.a(a) ,.b(b),.sum(sum),.cin(cin),.cout(cout));
	 
     initial begin
		 
         $monitor("a = %b ,b= %b , sum = %b , carry = %b ",a,b,sum,cout);
		 $dumpfile("fulladder.vcd");
		 $dumpvars;
a = 0; b = 0; cin = 0;#5
a = 0; b = 1; cin = 0;#5
a = 0; b = 2; cin = 0;#5
a = 0; b = 3; cin = 0;#5
a = 0; b = 4; cin = 0;#5
a = 0; b = 5; cin = 0;#5
a = 0; b = 6; cin = 0;#5
a = 0; b = 7; cin = 0;#5

a = 1; b = 0; cin = 0;#5
a = 1; b = 1; cin = 0;#5
a = 1; b = 2; cin = 0;#5
a = 1; b = 3; cin = 0;#5
a = 1; b = 4; cin = 0;#5
a = 1; b = 5; cin = 0;#5
a = 1; b = 6; cin = 0;#5
a = 1; b = 7; cin = 0;#5

a = 2; b = 0; cin = 0;#5
a = 2; b = 1; cin = 0;#5
a = 2; b = 2; cin = 0;#5
a = 2; b = 3; cin = 0;#5
a = 2; b = 4; cin = 0;#5
a = 2; b = 5; cin = 0;#5
a = 2; b = 6; cin = 0;#5
a = 2; b = 7; cin = 0;#5

a = 3; b = 0; cin = 0;#5
a = 3; b = 1; cin = 0;#5
a = 3; b = 2; cin = 0;#5
a = 3; b = 3; cin = 0;#5
a = 3; b = 4; cin = 0;#5
a = 3; b = 5; cin = 0;#5
a = 3; b = 6; cin = 0;#5
a = 3; b = 7; cin = 0;#5

a = 4; b = 0; cin = 0;#5
a = 4; b = 1; cin = 0;#5
a = 4; b = 2; cin = 0;#5
a = 4; b = 3; cin = 0;#5
a = 4; b = 4; cin = 0;#5
a = 4; b = 5; cin = 0;#5
a = 4; b = 6; cin = 0;#5
a = 4; b = 7; cin = 0;#5

a = 5; b = 0; cin = 0;#5
a = 5; b = 1; cin = 0;#5
a = 5; b = 2; cin = 0;#5
a = 5; b = 3; cin = 0;#5
a = 5; b = 4; cin = 0;#5
a = 5; b = 5; cin = 0;#5
a = 5; b = 6; cin = 0;#5
a = 5; b = 7; cin = 0;#5

a = 6; b = 0; cin = 0;#5
a = 6; b = 1; cin = 0;#5
a = 6; b = 2; cin = 0;#5
a = 6; b = 3; cin = 0;#5
a = 6; b = 4; cin = 0;#5
a = 6; b = 5; cin = 0;#5
a = 6; b = 6; cin = 0;#5
a = 6; b = 7; cin = 0;#5

a = 7; b = 0; cin = 0;#5
a = 7; b = 1; cin = 0;#5
a = 7; b = 2; cin = 0;#5
a = 7; b = 3; cin = 0;#5
a = 7; b = 4; cin = 0;#5
a = 7; b = 5; cin = 0;#5
a = 7; b = 6; cin = 0;#5
a = 7; b = 7; cin = 0;

end
 
endmodule

Full_Adder/fulladder.vcd
$date
	Mon Mar 19 18:35:27 2018
$end
$version
	Icarus Verilog
$end
$timescale
	1s
$end
$scope module tb_full_adder $end
$var wire 3 ! cout [2:0] $end
$var wire 3 " sum [2:0] $end
$var reg 3 # a [2:0] $end
$var reg 3 $ b [2:0] $end
$var reg 3 % cin [2:0] $end
$scope module Fa $end
$var wire 3 & a [2:0] $end
$var wire 3 ' b [2:0] $end
$var wire 3 ( cin [2:0] $end
$var wire 3 ) cout [2:0] $end
$var wire 3 * sum [2:0] $end
$upscope $end
$upscope $end
$enddefinitions $end
#0
$dumpvars
b0 *
b0 )
b0 (
b0 '
b0 &
b0 %
b0 $
b0 #
b0 "
b0 !
$end
#5
b1 "
b1 *
b1 $
b1 '
#10
b10 "
b10 *
b10 $
b10 '
#15
b11 "
b11 *
b11 $
b11 '
#20
b100 "
b100 *
b100 $
b100 '
#25
b101 "
b101 *
b101 $
b101 '
#30
b110 "
b110 *
b110 $
b110 '
#35
b111 "
b111 *
b111 $
b111 '
#40
b1 "
b1 *
b0 $
b0 '
b1 #
b1 &
#45
b0 "
b0 *
b1 !
b1 )
b1 $
b1 '
#50
b11 "
b11 *
b0 !
b0 )
b10 $
b10 '
#55
b10 "
b10 *
b1 !
b1 )
b11 $
b11 '
#60
b101 "
b101 *
b0 !
b0 )
b100 $
b100 '
#65
b100 "
b100 *
b1 !
b1 )
b101 $
b101 '
#70
b111 "
b111 *
b0 !
b0 )
b110 $
b110 '
#75
b110 "
b110 *
b1 !
b1 )
b111 $
b111 '
#80
b10 "
b10 *
b0 !
b0 )
b0 $
b0 '
b10 #
b10 &
#85
b11 "
b11 *
b1 $
b1 '
#90
b0 "
b0 *
b10 !
b10 )
b10 $
b10 '
#95
b1 "
b1 *
b11 $
b11 '
#100
b110 "
b110 *
b0 !
b0 )
b100 $
b100 '
#105
b111 "
b111 *
b101 $
b101 '
#110
b100 "
b100 *
b10 !
b10 )
b110 $
b110 '
#115
b101 "
b101 *
b111 $
b111 '
#120
b11 "
b11 *
b0 !
b0 )
b0 $
b0 '
b11 #
b11 &
#125
b10 "
b10 *
b1 !
b1 )
b1 $
b1 '
#130
b1 "
b1 *
b10 !
b10 )
b10 $
b10 '
#135
b0 "
b0 *
b11 !
b11 )
b11 $
b11 '
#140
b111 "
b111 *
b0 !
b0 )
b100 $
b100 '
#145
b110 "
b110 *
b1 !
b1 )
b101 $
b101 '
#150
b101 "
b101 *
b10 !
b10 )
b110 $
b110 '
#155
b100 "
b100 *
b11 !
b11 )
b111 $
b111 '
#160
b0 !
b0 )
b0 $
b0 '
b100 #
b100 &
#165
b101 "
b101 *
b1 $
b1 '
#170
b110 "
b110 *
b10 $
b10 '
#175
b111 "
b111 *
b11 $
b11 '
#180
b0 "
b0 *
b100 !
b100 )
b100 $
b100 '
#185
b1 "
b1 *
b101 $
b101 '
#190
b10 "
b10 *
b110 $
b110 '
#195
b11 "
b11 *
b111 $
b111 '
#200
b101 "
b101 *
b0 !
b0 )
b0 $
b0 '
b101 #
b101 &
#205
b100 "
b100 *
b1 !
b1 )
b1 $
b1 '
#210
b111 "
b111 *
b0 !
b0 )
b10 $
b10 '
#215
b110 "
b110 *
b1 !
b1 )
b11 $
b11 '
#220
b1 "
b1 *
b100 !
b100 )
b100 $
b100 '
#225
b0 "
b0 *
b101 !
b101 )
b101 $
b101 '
#230
b11 "
b11 *
b100 !
b100 )
b110 $
b110 '
#235
b10 "
b10 *
b101 !
b101 )
b111 $
b111 '
#240
b110 "
b110 *
b0 !
b0 )
b0 $
b0 '
b110 #
b110 &
#245
b111 "
b111 *
b1 $
b1 '
#250
b100 "
b100 *
b10 !
b10 )
b10 $
b10 '
#255
b101 "
b101 *
b11 $
b11 '
#260
b10 "
b10 *
b100 !
b100 )
b100 $
b100 '
#265
b11 "
b11 *
b101 $
b101 '
#270
b0 "
b0 *
b110 !
b110 )
b110 $
b110 '
#275
b1 "
b1 *
b111 $
b111 '
#280
b111 "
b111 *
b0 !
b0 )
b0 $
b0 '
b111 #
b111 &
#285
b110 "
b110 *
b1 !
b1 )
b1 $
b1 '
#290
b101 "
b101 *
b10 !
b10 )
b10 $
b10 '
#295
b100 "
b100 *
b11 !
b11 )
b11 $
b11 '
#300
b11 "
b11 *
b100 !
b100 )
b100 $
b100 '
#305
b10 "
b10 *
b101 !
b101 )
b101 $
b101 '
#310
b1 "
b1 *
b110 !
b110 )
b110 $
b110 '
#315
b0 "
b0 *
b111 !
b111 )
b111 $
b111 '
